<?xml version="1.0" encoding="UTF-8" standalone="yes"?>
<w:styles xmlns:mc="http://schemas.openxmlformats.org/markup-compatibility/2006" xmlns:r="http://schemas.openxmlformats.org/officeDocument/2006/relationships" xmlns:w="http://schemas.openxmlformats.org/wordprocessingml/2006/main" xmlns:w14="http://schemas.microsoft.com/office/word/2010/wordml" xmlns:w15="http://schemas.microsoft.com/office/word/2012/wordml" xmlns:w16se="http://schemas.microsoft.com/office/word/2015/wordml/symex" mc:Ignorable="w14 w15 w16se"><w:docDefaults><w:rPrDefault><w:rPr><w:rFonts w:ascii="Alstom" w:eastAsia="Times New Roman" w:hAnsi="Alstom" w:cs="Helvetica"/><w:lang w:val="en-US" w:eastAsia="en-US" w:bidi="ar-SA"/></w:rPr></w:rPrDefault><w:pPrDefault/></w:docDefaults><w:latentStyles w:defLockedState="0" w:defUIPriority="99" w:defSemiHidden="0" w:defUnhideWhenUsed="0" w:defQFormat="0" w:count="372"><w:lsdException w:name="Normal" w:uiPriority="0" w:qFormat="1"/><w:lsdException w:name="heading 1" w:uiPriority="0" w:qFormat="1"/><w:lsdException w:name="heading 2" w:uiPriority="0" w:qFormat="1"/><w:lsdException w:name="heading 3" w:uiPriority="0" w:qFormat="1"/><w:lsdException w:name="heading 4" w:uiPriority="0" w:qFormat="1"/><w:lsdException w:name="heading 5" w:uiPriority="0" w:qFormat="1"/><w:lsdException w:name="heading 6" w:uiPriority="0" w:qFormat="1"/><w:lsdException w:name="heading 7" w:uiPriority="0" w:qFormat="1"/><w:lsdException w:name="heading 8" w:uiPriority="0" w:qFormat="1"/><w:lsdException w:name="heading 9" w:uiPriority="0" w:qFormat="1"/><w:lsdException w:name="index 1" w:semiHidden="1" w:unhideWhenUsed="1"/><w:lsdException w:name="index 2" w:semiHidden="1" w:unhideWhenUsed="1"/><w:lsdException w:name="index 3" w:semiHidden="1" w:unhideWhenUsed="1"/><w:lsdException w:name="index 4" w:semiHidden="1" w:unhideWhenUsed="1"/><w:lsdException w:name="index 5" w:semiHidden="1" w:unhideWhenUsed="1"/><w:lsdException w:name="index 6" w:semiHidden="1" w:unhideWhenUsed="1"/><w:lsdException w:name="index 7" w:semiHidden="1" w:unhideWhenUsed="1"/><w:lsdException w:name="index 8" w:semiHidden="1" w:unhideWhenUsed="1"/><w:lsdException w:name="index 9" w:semiHidden="1" w:unhideWhenUsed="1"/><w:lsdException w:name="toc 1" w:semiHidden="1" w:uiPriority="39" w:unhideWhenUsed="1" w:qFormat="1"/><w:lsdException w:name="toc 2" w:semiHidden="1" w:uiPriority="39" w:unhideWhenUsed="1" w:qFormat="1"/><w:lsdException w:name="toc 3" w:semiHidden="1" w:uiPriority="39" w:unhideWhenUsed="1" w:qFormat="1"/><w:lsdException w:name="toc 4" w:semiHidden="1" w:uiPriority="39" w:unhideWhenUsed="1"/><w:lsdException w:name="toc 5" w:semiHidden="1" w:uiPriority="39" w:unhideWhenUsed="1"/><w:lsdException w:name="toc 6" w:semiHidden="1" w:uiPriority="39" w:unhideWhenUsed="1"/><w:lsdException w:name="toc 7" w:semiHidden="1" w:uiPriority="39" w:unhideWhenUsed="1"/><w:lsdException w:name="toc 8" w:semiHidden="1" w:uiPriority="39" w:unhideWhenUsed="1"/><w:lsdException w:name="toc 9" w:semiHidden="1" w:uiPriority="39" w:unhideWhenUsed="1"/><w:lsdException w:name="Normal Indent" w:semiHidden="1" w:unhideWhenUsed="1"/><w:lsdException w:name="footnote text" w:semiHidden="1" w:unhideWhenUsed="1"/><w:lsdException w:name="annotation text" w:semiHidden="1" w:unhideWhenUsed="1"/><w:lsdException w:name="header" w:semiHidden="1" w:uiPriority="0" w:unhideWhenUsed="1"/><w:lsdException w:name="footer" w:semiHidden="1" w:uiPriority="0" w:unhideWhenUsed="1"/><w:lsdException w:name="index heading" w:semiHidden="1" w:unhideWhenUsed="1"/><w:lsdException w:name="caption" w:semiHidden="1" w:uiPriority="0" w:unhideWhenUsed="1" w:qFormat="1"/><w:lsdException w:name="table of figures" w:semiHidden="1" w:unhideWhenUsed="1"/><w:lsdException w:name="envelope address" w:semiHidden="1" w:unhideWhenUsed="1"/><w:lsdException w:name="envelope return" w:semiHidden="1" w:unhideWhenUsed="1"/><w:lsdException w:name="footnote reference" w:semiHidden="1" w:uiPriority="0" w:unhideWhenUsed="1"/><w:lsdException w:name="annotation reference" w:semiHidden="1" w:unhideWhenUsed="1"/><w:lsdException w:name="line number" w:semiHidden="1" w:unhideWhenUsed="1"/><w:lsdException w:name="page number" w:semiHidden="1" w:unhideWhenUsed="1"/><w:lsdException w:name="endnote reference" w:semiHidden="1" w:unhideWhenUsed="1"/><w:lsdException w:name="endnote text" w:semiHidden="1" w:unhideWhenUsed="1"/><w:lsdException w:name="table of authorities" w:semiHidden="1" w:unhideWhenUsed="1"/><w:lsdException w:name="macro" w:semiHidden="1" w:unhideWhenUsed="1"/><w:lsdException w:name="toa heading" w:semiHidden="1" w:unhideWhenUsed="1"/><w:lsdException w:name="List" w:semiHidden="1" w:unhideWhenUsed="1"/><w:lsdException w:name="List Bullet" w:semiHidden="1" w:unhideWhenUsed="1"/><w:lsdException w:name="List Number" w:semiHidden="1" w:unhideWhenUsed="1"/><w:lsdException w:name="List 2" w:semiHidden="1" w:unhideWhenUsed="1"/><w:lsdException w:name="List 3" w:semiHidden="1" w:unhideWhenUsed="1"/><w:lsdException w:name="List 4" w:semiHidden="1" w:unhideWhenUsed="1"/><w:lsdException w:name="List 5" w:semiHidden="1" w:unhideWhenUsed="1"/><w:lsdException w:name="List Bullet 2" w:semiHidden="1" w:unhideWhenUsed="1"/><w:lsdException w:name="List Bullet 3" w:semiHidden="1" w:unhideWhenUsed="1"/><w:lsdException w:name="List Bullet 4" w:semiHidden="1" w:unhideWhenUsed="1"/><w:lsdException w:name="List Bullet 5" w:semiHidden="1" w:unhideWhenUsed="1"/><w:lsdException w:name="List Number 2" w:semiHidden="1" w:unhideWhenUsed="1"/><w:lsdException w:name="List Number 3" w:semiHidden="1" w:unhideWhenUsed="1"/><w:lsdException w:name="List Number 4" w:semiHidden="1" w:unhideWhenUsed="1"/><w:lsdException w:name="List Number 5" w:semiHidden="1" w:unhideWhenUsed="1"/><w:lsdException w:name="Title" w:uiPriority="10" w:qFormat="1"/><w:lsdException w:name="Closing" w:semiHidden="1" w:unhideWhenUsed="1"/><w:lsdException w:name="Signature" w:semiHidden="1" w:unhideWhenUsed="1"/><w:lsdException w:name="Default Paragraph Font" w:semiHidden="1" w:uiPriority="1" w:unhideWhenUsed="1"/><w:lsdException w:name="Body Text" w:semiHidden="1" w:unhideWhenUsed="1"/><w:lsdException w:name="Body Text Indent" w:semiHidden="1" w:unhideWhenUsed="1"/><w:lsdException w:name="List Continue" w:semiHidden="1" w:unhideWhenUsed="1"/><w:lsdException w:name="List Continue 2" w:semiHidden="1" w:unhideWhenUsed="1"/><w:lsdException w:name="List Continue 3" w:semiHidden="1" w:unhideWhenUsed="1"/><w:lsdException w:name="List Continue 4" w:semiHidden="1" w:unhideWhenUsed="1"/><w:lsdException w:name="List Continue 5" w:semiHidden="1" w:unhideWhenUsed="1"/><w:lsdException w:name="Message Header" w:semiHidden="1" w:unhideWhenUsed="1"/><w:lsdException w:name="Subtitle" w:uiPriority="11" w:qFormat="1"/><w:lsdException w:name="Salutation" w:semiHidden="1" w:unhideWhenUsed="1"/><w:lsdException w:name="Date" w:semiHidden="1" w:unhideWhenUsed="1"/><w:lsdException w:name="Body Text First Indent" w:semiHidden="1" w:unhideWhenUsed="1"/><w:lsdException w:name="Body Text First Indent 2" w:semiHidden="1" w:unhideWhenUsed="1"/><w:lsdException w:name="Note Heading" w:semiHidden="1" w:unhideWhenUsed="1"/><w:lsdException w:name="Body Text 2" w:semiHidden="1" w:unhideWhenUsed="1"/><w:lsdException w:name="Body Text 3" w:semiHidden="1" w:unhideWhenUsed="1"/><w:lsdException w:name="Body Text Indent 2" w:semiHidden="1" w:unhideWhenUsed="1"/><w:lsdException w:name="Body Text Indent 3" w:semiHidden="1" w:uiPriority="0" w:unhideWhenUsed="1"/><w:lsdException w:name="Block Text" w:semiHidden="1" w:unhideWhenUsed="1"/><w:lsdException w:name="Hyperlink" w:semiHidden="1" w:unhideWhenUsed="1"/><w:lsdException w:name="FollowedHyperlink" w:semiHidden="1" w:unhideWhenUsed="1"/><w:lsdException w:name="Strong" w:uiPriority="22" w:qFormat="1"/><w:lsdException w:name="Emphasis" w:uiPriority="20" w:qFormat="1"/><w:lsdException w:name="Document Map" w:semiHidden="1" w:unhideWhenUsed="1"/><w:lsdException w:name="Plain Text" w:semiHidden="1" w:unhideWhenUsed="1"/><w:lsdException w:name="E-mail Signature" w:semiHidden="1" w:unhideWhenUsed="1"/><w:lsdException w:name="HTML Top of Form" w:semiHidden="1" w:unhideWhenUsed="1"/><w:lsdException w:name="HTML Bottom of Form" w:semiHidden="1" w:unhideWhenUsed="1"/><w:lsdException w:name="Normal (Web)" w:semiHidden="1" w:unhideWhenUsed="1"/><w:lsdException w:name="HTML Acronym" w:semiHidden="1" w:unhideWhenUsed="1"/><w:lsdException w:name="HTML Address" w:semiHidden="1" w:unhideWhenUsed="1"/><w:lsdException w:name="HTML Cite" w:semiHidden="1" w:unhideWhenUsed="1"/><w:lsdException w:name="HTML Code" w:semiHidden="1" w:unhideWhenUsed="1"/><w:lsdException w:name="HTML Definition" w:semiHidden="1" w:unhideWhenUsed="1"/><w:lsdException w:name="HTML Keyboard" w:semiHidden="1" w:unhideWhenUsed="1"/><w:lsdException w:name="HTML Preformatted" w:semiHidden="1" w:unhideWhenUsed="1"/><w:lsdException w:name="HTML Sample" w:semiHidden="1" w:unhideWhenUsed="1"/><w:lsdException w:name="HTML Typewriter" w:semiHidden="1" w:unhideWhenUsed="1"/><w:lsdException w:name="HTML Variable" w:semiHidden="1" w:unhideWhenUsed="1"/><w:lsdException w:name="Normal Table" w:semiHidden="1" w:unhideWhenUsed="1"/><w:lsdException w:name="annotation subject" w:semiHidden="1" w:unhideWhenUsed="1"/><w:lsdException w:name="No List" w:semiHidden="1" w:unhideWhenUsed="1"/><w:lsdException w:name="Outline List 1" w:semiHidden="1" w:unhideWhenUsed="1"/><w:lsdException w:name="Outline List 2" w:semiHidden="1" w:unhideWhenUsed="1"/><w:lsdException w:name="Outline List 3" w:semiHidden="1" w:unhideWhenUsed="1"/><w:lsdException w:name="Table Simple 1" w:semiHidden="1" w:unhideWhenUsed="1"/><w:lsdException w:name="Table Simple 2" w:semiHidden="1" w:unhideWhenUsed="1"/><w:lsdException w:name="Table Simple 3" w:semiHidden="1" w:unhideWhenUsed="1"/><w:lsdException w:name="Table Classic 1" w:semiHidden="1" w:unhideWhenUsed="1"/><w:lsdException w:name="Table Classic 2" w:semiHidden="1" w:unhideWhenUsed="1"/><w:lsdException w:name="Table Classic 3" w:semiHidden="1" w:unhideWhenUsed="1"/><w:lsdException w:name="Table Classic 4" w:semiHidden="1" w:unhideWhenUsed="1"/><w:lsdException w:name="Table Colorful 1" w:semiHidden="1" w:unhideWhenUsed="1"/><w:lsdException w:name="Table Colorful 2" w:semiHidden="1" w:unhideWhenUsed="1"/><w:lsdException w:name="Table Colorful 3" w:semiHidden="1" w:unhideWhenUsed="1"/><w:lsdException w:name="Table Columns 1" w:semiHidden="1" w:unhideWhenUsed="1"/><w:lsdException w:name="Table Columns 2" w:semiHidden="1" w:unhideWhenUsed="1"/><w:lsdException w:name="Table Columns 3" w:semiHidden="1" w:unhideWhenUsed="1"/><w:lsdException w:name="Table Columns 4" w:semiHidden="1" w:unhideWhenUsed="1"/><w:lsdException w:name="Table Columns 5" w:semiHidden="1" w:unhideWhenUsed="1"/><w:lsdException w:name="Table Grid 1" w:semiHidden="1" w:unhideWhenUsed="1"/><w:lsdException w:name="Table Grid 2" w:semiHidden="1" w:unhideWhenUsed="1"/><w:lsdException w:name="Table Grid 3" w:semiHidden="1" w:unhideWhenUsed="1"/><w:lsdException w:name="Table Grid 4" w:semiHidden="1" w:unhideWhenUsed="1"/><w:lsdException w:name="Table Grid 5" w:semiHidden="1" w:unhideWhenUsed="1"/><w:lsdException w:name="Table Grid 6" w:semiHidden="1" w:unhideWhenUsed="1"/><w:lsdException w:name="Table Grid 7" w:semiHidden="1" w:unhideWhenUsed="1"/><w:lsdException w:name="Table Grid 8" w:semiHidden="1" w:unhideWhenUsed="1"/><w:lsdException w:name="Table List 1" w:semiHidden="1" w:unhideWhenUsed="1"/><w:lsdException w:name="Table List 2" w:semiHidden="1" w:unhideWhenUsed="1"/><w:lsdException w:name="Table List 3" w:semiHidden="1" w:unhideWhenUsed="1"/><w:lsdException w:name="Table List 4" w:semiHidden="1" w:unhideWhenUsed="1"/><w:lsdException w:name="Table List 5" w:semiHidden="1" w:unhideWhenUsed="1"/><w:lsdException w:name="Table List 6" w:semiHidden="1" w:unhideWhenUsed="1"/><w:lsdException w:name="Table List 7" w:semiHidden="1" w:unhideWhenUsed="1"/><w:lsdException w:name="Table List 8" w:semiHidden="1" w:unhideWhenUsed="1"/><w:lsdException w:name="Table 3D effects 1" w:semiHidden="1" w:unhideWhenUsed="1"/><w:lsdException w:name="Table 3D effects 2" w:semiHidden="1" w:unhideWhenUsed="1"/><w:lsdException w:name="Table 3D effects 3" w:semiHidden="1" w:unhideWhenUsed="1"/><w:lsdException w:name="Table Contemporary" w:semiHidden="1" w:unhideWhenUsed="1"/><w:lsdException w:name="Table Elegant" w:semiHidden="1" w:unhideWhenUsed="1"/><w:lsdException w:name="Table Professional" w:semiHidden="1" w:unhideWhenUsed="1"/><w:lsdException w:name="Table Subtle 1" w:semiHidden="1" w:unhideWhenUsed="1"/><w:lsdException w:name="Table Subtle 2" w:semiHidden="1" w:unhideWhenUsed="1"/><w:lsdException w:name="Table Web 1" w:semiHidden="1" w:unhideWhenUsed="1"/><w:lsdException w:name="Table Web 2" w:semiHidden="1" w:unhideWhenUsed="1"/><w:lsdException w:name="Table Web 3" w:semiHidden="1" w:unhideWhenUsed="1"/><w:lsdException w:name="Balloon Text" w:semiHidden="1" w:unhideWhenUsed="1"/><w:lsdException w:name="Table Grid" w:uiPriority="0"/><w:lsdException w:name="Table Theme" w:semiHidden="1" w:unhideWhenUsed="1"/><w:lsdException w:name="Placeholder Text" w:semiHidden="1"/><w:lsdException w:name="No Spacing" w:uiPriority="1" w:qFormat="1"/><w:lsdException w:name="Light Shading" w:uiPriority="60"/><w:lsdException w:name="Light List" w:uiPriority="61"/><w:lsdException w:name="Light Grid" w:uiPriority="62"/><w:lsdException w:name="Medium Shading 1" w:uiPriority="63"/><w:lsdException w:name="Medium Shading 2" w:uiPriority="64"/><w:lsdException w:name="Medium List 1" w:uiPriority="65"/><w:lsdException w:name="Medium List 2" w:uiPriority="66"/><w:lsdException w:name="Medium Grid 1" w:uiPriority="67"/><w:lsdException w:name="Medium Grid 2" w:uiPriority="68"/><w:lsdException w:name="Medium Grid 3" w:uiPriority="69"/><w:lsdException w:name="Dark List" w:uiPriority="70"/><w:lsdException w:name="Colorful Shading" w:uiPriority="71"/><w:lsdException w:name="Colorful List" w:uiPriority="72"/><w:lsdException w:name="Colorful Grid" w:uiPriority="73"/><w:lsdException w:name="Light Shading Accent 1" w:uiPriority="60"/><w:lsdException w:name="Light List Accent 1" w:uiPriority="61"/><w:lsdException w:name="Light Grid Accent 1" w:uiPriority="62"/><w:lsdException w:name="Medium Shading 1 Accent 1" w:uiPriority="63"/><w:lsdException w:name="Medium Shading 2 Accent 1" w:uiPriority="64"/><w:lsdException w:name="Medium List 1 Accent 1" w:uiPriority="65"/><w:lsdException w:name="Revision" w:semiHidden="1"/><w:lsdException w:name="List Paragraph" w:uiPriority="34" w:qFormat="1"/><w:lsdException w:name="Quote" w:uiPriority="29" w:qFormat="1"/><w:lsdException w:name="Intense Quote" w:uiPriority="30" w:qFormat="1"/><w:lsdException w:name="Medium List 2 Accent 1" w:uiPriority="66"/><w:lsdException w:name="Medium Grid 1 Accent 1" w:uiPriority="67"/><w:lsdException w:name="Medium Grid 2 Accent 1" w:uiPriority="68"/><w:lsdException w:name="Medium Grid 3 Accent 1" w:uiPriority="69"/><w:lsdException w:name="Dark List Accent 1" w:uiPriority="70"/><w:lsdException w:name="Colorful Shading Accent 1" w:uiPriority="71"/><w:lsdException w:name="Colorful List Accent 1" w:uiPriority="72"/><w:lsdException w:name="Colorful Grid Accent 1" w:uiPriority="73"/><w:lsdException w:name="Light Shading Accent 2" w:uiPriority="60"/><w:lsdException w:name="Light List Accent 2" w:uiPriority="61"/><w:lsdException w:name="Light Grid Accent 2" w:uiPriority="62"/><w:lsdException w:name="Medium Shading 1 Accent 2" w:uiPriority="63"/><w:lsdException w:name="Medium Shading 2 Accent 2" w:uiPriority="64"/><w:lsdException w:name="Medium List 1 Accent 2" w:uiPriority="65"/><w:lsdException w:name="Medium List 2 Accent 2" w:uiPriority="66"/><w:lsdException w:name="Medium Grid 1 Accent 2" w:uiPriority="67"/><w:lsdException w:name="Medium Grid 2 Accent 2" w:uiPriority="68"/><w:lsdException w:name="Medium Grid 3 Accent 2" w:uiPriority="69"/><w:lsdException w:name="Dark List Accent 2" w:uiPriority="70"/><w:lsdException w:name="Colorful Shading Accent 2" w:uiPriority="71"/><w:lsdException w:name="Colorful List Accent 2" w:uiPriority="72"/><w:lsdException w:name="Colorful Grid Accent 2" w:uiPriority="73"/><w:lsdException w:name="Light Shading Accent 3" w:uiPriority="60"/><w:lsdException w:name="Light List Accent 3" w:uiPriority="61"/><w:lsdException w:name="Light Grid Accent 3" w:uiPriority="62"/><w:lsdException w:name="Medium Shading 1 Accent 3" w:uiPriority="63"/><w:lsdException w:name="Medium Shading 2 Accent 3" w:uiPriority="64"/><w:lsdException w:name="Medium List 1 Accent 3" w:uiPriority="65"/><w:lsdException w:name="Medium List 2 Accent 3" w:uiPriority="66"/><w:lsdException w:name="Medium Grid 1 Accent 3" w:uiPriority="67"/><w:lsdException w:name="Medium Grid 2 Accent 3" w:uiPriority="68"/><w:lsdException w:name="Medium Grid 3 Accent 3" w:uiPriority="69"/><w:lsdException w:name="Dark List Accent 3" w:uiPriority="70"/><w:lsdException w:name="Colorful Shading Accent 3" w:uiPriority="71"/><w:lsdException w:name="Colorful List Accent 3" w:uiPriority="72"/><w:lsdException w:name="Colorful Grid Accent 3" w:uiPriority="73"/><w:lsdException w:name="Light Shading Accent 4" w:uiPriority="60"/><w:lsdException w:name="Light List Accent 4" w:uiPriority="61"/><w:lsdException w:name="Light Grid Accent 4" w:uiPriority="62"/><w:lsdException w:name="Medium Shading 1 Accent 4" w:uiPriority="63"/><w:lsdException w:name="Medium Shading 2 Accent 4" w:uiPriority="64"/><w:lsdException w:name="Medium List 1 Accent 4" w:uiPriority="65"/><w:lsdException w:name="Medium List 2 Accent 4" w:uiPriority="66"/><w:lsdException w:name="Medium Grid 1 Accent 4" w:uiPriority="67"/><w:lsdException w:name="Medium Grid 2 Accent 4" w:uiPriority="68"/><w:lsdException w:name="Medium Grid 3 Accent 4" w:uiPriority="69"/><w:lsdException w:name="Dark List Accent 4" w:uiPriority="70"/><w:lsdException w:name="Colorful Shading Accent 4" w:uiPriority="71"/><w:lsdException w:name="Colorful List Accent 4" w:uiPriority="72"/><w:lsdException w:name="Colorful Grid Accent 4" w:uiPriority="73"/><w:lsdException w:name="Light Shading Accent 5" w:uiPriority="60"/><w:lsdException w:name="Light List Accent 5" w:uiPriority="61"/><w:lsdException w:name="Light Grid Accent 5" w:uiPriority="62"/><w:lsdException w:name="Medium Shading 1 Accent 5" w:uiPriority="63"/><w:lsdException w:name="Medium Shading 2 Accent 5" w:uiPriority="64"/><w:lsdException w:name="Medium List 1 Accent 5" w:uiPriority="65"/><w:lsdException w:name="Medium List 2 Accent 5" w:uiPriority="66"/><w:lsdException w:name="Medium Grid 1 Accent 5" w:uiPriority="67"/><w:lsdException w:name="Medium Grid 2 Accent 5" w:uiPriority="68"/><w:lsdException w:name="Medium Grid 3 Accent 5" w:uiPriority="69"/><w:lsdException w:name="Dark List Accent 5" w:uiPriority="70"/><w:lsdException w:name="Colorful Shading Accent 5" w:uiPriority="71"/><w:lsdException w:name="Colorful List Accent 5" w:uiPriority="72"/><w:lsdException w:name="Colorful Grid Accent 5" w:uiPriority="73"/><w:lsdException w:name="Light Shading Accent 6" w:uiPriority="60"/><w:lsdException w:name="Light List Accent 6" w:uiPriority="61"/><w:lsdException w:name="Light Grid Accent 6" w:uiPriority="62"/><w:lsdException w:name="Medium Shading 1 Accent 6" w:uiPriority="63"/><w:lsdException w:name="Medium Shading 2 Accent 6" w:uiPriority="64"/><w:lsdException w:name="Medium List 1 Accent 6" w:uiPriority="65"/><w:lsdException w:name="Medium List 2 Accent 6" w:uiPriority="66"/><w:lsdException w:name="Medium Grid 1 Accent 6" w:uiPriority="67"/><w:lsdException w:name="Medium Grid 2 Accent 6" w:uiPriority="68"/><w:lsdException w:name="Medium Grid 3 Accent 6" w:uiPriority="69"/><w:lsdException w:name="Dark List Accent 6" w:uiPriority="70"/><w:lsdException w:name="Colorful Shading Accent 6" w:uiPriority="71"/><w:lsdException w:name="Colorful List Accent 6" w:uiPriority="72"/><w:lsdException w:name="Colorful Grid Accent 6" w:uiPriority="73"/><w:lsdException w:name="Subtle Emphasis" w:uiPriority="19" w:qFormat="1"/><w:lsdException w:name="Intense Emphasis" w:uiPriority="21" w:qFormat="1"/><w:lsdException w:name="Subtle Reference" w:uiPriority="31" w:qFormat="1"/><w:lsdException w:name="Intense Reference" w:uiPriority="32" w:qFormat="1"/><w:lsdException w:name="Book Title" w:uiPriority="33" w:qFormat="1"/><w:lsdException w:name="Bibliography" w:semiHidden="1" w:uiPriority="37" w:unhideWhenUsed="1"/><w:lsdException w:name="TOC Heading" w:semiHidden="1" w:uiPriority="39" w:unhideWhenUsed="1" w:qFormat="1"/><w:lsdException w:name="Plain Table 1" w:uiPriority="41"/><w:lsdException w:name="Plain Table 2" w:uiPriority="42"/><w:lsdException w:name="Plain Table 3" w:uiPriority="43"/><w:lsdException w:name="Plain Table 4" w:uiPriority="44"/><w:lsdException w:name="Plain Table 5" w:uiPriority="45"/><w:lsdException w:name="Grid Table Light" w:uiPriority="40"/><w:lsdException w:name="Grid Table 1 Light" w:uiPriority="46"/><w:lsdException w:name="Grid Table 2" w:uiPriority="47"/><w:lsdException w:name="Grid Table 3" w:uiPriority="48"/><w:lsdException w:name="Grid Table 4" w:uiPriority="49"/><w:lsdException w:name="Grid Table 5 Dark" w:uiPriority="50"/><w:lsdException w:name="Grid Table 6 Colorful" w:uiPriority="51"/><w:lsdException w:name="Grid Table 7 Colorful" w:uiPriority="52"/><w:lsdException w:name="Grid Table 1 Light Accent 1" w:uiPriority="46"/><w:lsdException w:name="Grid Table 2 Accent 1" w:uiPriority="47"/><w:lsdException w:name="Grid Table 3 Accent 1" w:uiPriority="48"/><w:lsdException w:name="Grid Table 4 Accent 1" w:uiPriority="49"/><w:lsdException w:name="Grid Table 5 Dark Accent 1" w:uiPriority="50"/><w:lsdException w:name="Grid Table 6 Colorful Accent 1" w:uiPriority="51"/><w:lsdException w:name="Grid Table 7 Colorful Accent 1" w:uiPriority="52"/><w:lsdException w:name="Grid Table 1 Light Accent 2" w:uiPriority="46"/><w:lsdException w:name="Grid Table 2 Accent 2" w:uiPriority="47"/><w:lsdException w:name="Grid Table 3 Accent 2" w:uiPriority="48"/><w:lsdException w:name="Grid Table 4 Accent 2" w:uiPriority="49"/><w:lsdException w:name="Grid Table 5 Dark Accent 2" w:uiPriority="50"/><w:lsdException w:name="Grid Table 6 Colorful Accent 2" w:uiPriority="51"/><w:lsdException w:name="Grid Table 7 Colorful Accent 2" w:uiPriority="52"/><w:lsdException w:name="Grid Table 1 Light Accent 3" w:uiPriority="46"/><w:lsdException w:name="Grid Table 2 Accent 3" w:uiPriority="47"/><w:lsdException w:name="Grid Table 3 Accent 3" w:uiPriority="48"/><w:lsdException w:name="Grid Table 4 Accent 3" w:uiPriority="49"/><w:lsdException w:name="Grid Table 5 Dark Accent 3" w:uiPriority="50"/><w:lsdException w:name="Grid Table 6 Colorful Accent 3" w:uiPriority="51"/><w:lsdException w:name="Grid Table 7 Colorful Accent 3" w:uiPriority="52"/><w:lsdException w:name="Grid Table 1 Light Accent 4" w:uiPriority="46"/><w:lsdException w:name="Grid Table 2 Accent 4" w:uiPriority="47"/><w:lsdException w:name="Grid Table 3 Accent 4" w:uiPriority="48"/><w:lsdException w:name="Grid Table 4 Accent 4" w:uiPriority="49"/><w:lsdException w:name="Grid Table 5 Dark Accent 4" w:uiPriority="50"/><w:lsdException w:name="Grid Table 6 Colorful Accent 4" w:uiPriority="51"/><w:lsdException w:name="Grid Table 7 Colorful Accent 4" w:uiPriority="52"/><w:lsdException w:name="Grid Table 1 Light Accent 5" w:uiPriority="46"/><w:lsdException w:name="Grid Table 2 Accent 5" w:uiPriority="47"/><w:lsdException w:name="Grid Table 3 Accent 5" w:uiPriority="48"/><w:lsdException w:name="Grid Table 4 Accent 5" w:uiPriority="49"/><w:lsdException w:name="Grid Table 5 Dark Accent 5" w:uiPriority="50"/><w:lsdException w:name="Grid Table 6 Colorful Accent 5" w:uiPriority="51"/><w:lsdException w:name="Grid Table 7 Colorful Accent 5" w:uiPriority="52"/><w:lsdException w:name="Grid Table 1 Light Accent 6" w:uiPriority="46"/><w:lsdException w:name="Grid Table 2 Accent 6" w:uiPriority="47"/><w:lsdException w:name="Grid Table 3 Accent 6" w:uiPriority="48"/><w:lsdException w:name="Grid Table 4 Accent 6" w:uiPriority="49"/><w:lsdException w:name="Grid Table 5 Dark Accent 6" w:uiPriority="50"/><w:lsdException w:name="Grid Table 6 Colorful Accent 6" w:uiPriority="51"/><w:lsdException w:name="Grid Table 7 Colorful Accent 6" w:uiPriority="52"/><w:lsdException w:name="List Table 1 Light" w:uiPriority="46"/><w:lsdException w:name="List Table 2" w:uiPriority="47"/><w:lsdException w:name="List Table 3" w:uiPriority="48"/><w:lsdException w:name="List Table 4" w:uiPriority="49"/><w:lsdException w:name="List Table 5 Dark" w:uiPriority="50"/><w:lsdException w:name="List Table 6 Colorful" w:uiPriority="51"/><w:lsdException w:name="List Table 7 Colorful" w:uiPriority="52"/><w:lsdException w:name="List Table 1 Light Accent 1" w:uiPriority="46"/><w:lsdException w:name="List Table 2 Accent 1" w:uiPriority="47"/><w:lsdException w:name="List Table 3 Accent 1" w:uiPriority="48"/><w:lsdException w:name="List Table 4 Accent 1" w:uiPriority="49"/><w:lsdException w:name="List Table 5 Dark Accent 1" w:uiPriority="50"/><w:lsdException w:name="List Table 6 Colorful Accent 1" w:uiPriority="51"/><w:lsdException w:name="List Table 7 Colorful Accent 1" w:uiPriority="52"/><w:lsdException w:name="List Table 1 Light Accent 2" w:uiPriority="46"/><w:lsdException w:name="List Table 2 Accent 2" w:uiPriority="47"/><w:lsdException w:name="List Table 3 Accent 2" w:uiPriority="48"/><w:lsdException w:name="List Table 4 Accent 2" w:uiPriority="49"/><w:lsdException w:name="List Table 5 Dark Accent 2" w:uiPriority="50"/><w:lsdException w:name="List Table 6 Colorful Accent 2" w:uiPriority="51"/><w:lsdException w:name="List Table 7 Colorful Accent 2" w:uiPriority="52"/><w:lsdException w:name="List Table 1 Light Accent 3" w:uiPriority="46"/><w:lsdException w:name="List Table 2 Accent 3" w:uiPriority="47"/><w:lsdException w:name="List Table 3 Accent 3" w:uiPriority="48"/><w:lsdException w:name="List Table 4 Accent 3" w:uiPriority="49"/><w:lsdException w:name="List Table 5 Dark Accent 3" w:uiPriority="50"/><w:lsdException w:name="List Table 6 Colorful Accent 3" w:uiPriority="51"/><w:lsdException w:name="List Table 7 Colorful Accent 3" w:uiPriority="52"/><w:lsdException w:name="List Table 1 Light Accent 4" w:uiPriority="46"/><w:lsdException w:name="List Table 2 Accent 4" w:uiPriority="47"/><w:lsdException w:name="List Table 3 Accent 4" w:uiPriority="48"/><w:lsdException w:name="List Table 4 Accent 4" w:uiPriority="49"/><w:lsdException w:name="List Table 5 Dark Accent 4" w:uiPriority="50"/><w:lsdException w:name="List Table 6 Colorful Accent 4" w:uiPriority="51"/><w:lsdException w:name="List Table 7 Colorful Accent 4" w:uiPriority="52"/><w:lsdException w:name="List Table 1 Light Accent 5" w:uiPriority="46"/><w:lsdException w:name="List Table 2 Accent 5" w:uiPriority="47"/><w:lsdException w:name="List Table 3 Accent 5" w:uiPriority="48"/><w:lsdException w:name="List Table 4 Accent 5" w:uiPriority="49"/><w:lsdException w:name="List Table 5 Dark Accent 5" w:uiPriority="50"/><w:lsdException w:name="List Table 6 Colorful Accent 5" w:uiPriority="51"/><w:lsdException w:name="List Table 7 Colorful Accent 5" w:uiPriority="52"/><w:lsdException w:name="List Table 1 Light Accent 6" w:uiPriority="46"/><w:lsdException w:name="List Table 2 Accent 6" w:uiPriority="47"/><w:lsdException w:name="List Table 3 Accent 6" w:uiPriority="48"/><w:lsdException w:name="List Table 4 Accent 6" w:uiPriority="49"/><w:lsdException w:name="List Table 5 Dark Accent 6" w:uiPriority="50"/><w:lsdException w:name="List Table 6 Colorful Accent 6" w:uiPriority="51"/><w:lsdException w:name="List Table 7 Colorful Accent 6" w:uiPriority="52"/><w:lsdException w:name="Mention" w:semiHidden="1" w:unhideWhenUsed="1"/></w:latentStyles><w:style w:type="paragraph" w:default="1" w:styleId="Normal"><w:name w:val="Normal"/><w:qFormat/><w:pPr><w:jc w:val="both"/></w:pPr><w:rPr><w:lang w:val="it-IT" w:eastAsia="it-IT"/></w:rPr></w:style><w:style w:type="paragraph" w:styleId="Heading1"><w:name w:val="heading 1"/><w:aliases w:val="Subtitle1,überschrift 1,H1,Heading 11,título 1,-&gt;PART 1,ERMH1,ERMH11,ERMH12,ERMH13,ERMH14,ERMH15,ERMH16,ERMH17,ERMH18,ERMH19,ERMH110,ERMH111,ERMH112,ERMH113,ERMH114,ERMH115,ERMH116,ERMH117,ERMH118,ERMH119,ERMH120,ERMH121,1 ghost,g,gho"/><w:basedOn w:val="Normal"/><w:next w:val="Normal"/><w:qFormat/><w:pPr><w:widowControl w:val="0"/><w:numPr><w:numId w:val="2"/></w:numPr><w:spacing w:before="360"/><w:jc w:val="left"/><w:outlineLvl w:val="0"/></w:pPr><w:rPr><w:b/><w:bCs/><w:caps/><w:sz w:val="24"/><w:szCs w:val="24"/></w:rPr></w:style><w:style w:type="paragraph" w:styleId="Heading2"><w:name w:val="heading 2"/><w:aliases w:val="subtitle2,Titre 2 modified,H2,h2,2,sub-sect,RFQ1,section header,21,sub-sect1,22,sub-sect2,23,sub-sect3,24,sub-sect4,25,sub-sect5,(1.1,1.2,1.3 etc),211,sub-sect11,Major,Major1,Major2,Major11,heading 2,1.1.1 heading,2 headline,h,título "/><w:basedOn w:val="Normal"/><w:next w:val="Normal"/><w:link w:val="Heading2Char"/><w:qFormat/><w:pPr><w:numPr><w:ilvl w:val="1"/><w:numId w:val="2"/></w:numPr><w:tabs><w:tab w:val="left" w:pos="709"/></w:tabs><w:spacing w:before="240"/><w:outlineLvl w:val="1"/></w:pPr><w:rPr><w:b/><w:bCs/><w:sz w:val="24"/><w:szCs w:val="24"/></w:rPr></w:style><w:style w:type="paragraph" w:styleId="Heading3"><w:name w:val="heading 3"/><w:aliases w:val="subtitle 3,3numbers,H3,Heading,Heading v,Heading 31,título 3,SubSub,SubSub1,SubSub2,SubSub3,SubSub4,SubSub5,SubSub6,SubSub7,SubSub8,SubSub9,-&gt;A.,ERMH3,ERMH31,ERMH32,ERMH33,ERMH34,ERMH35,ERMH36,ERMH37,ERMH38,ERMH39,ERMH310,ERMH311,b,§"/><w:basedOn w:val="Normal"/><w:next w:val="Normal"/><w:qFormat/><w:pPr><w:numPr><w:ilvl w:val="2"/><w:numId w:val="2"/></w:numPr><w:spacing w:before="240"/><w:outlineLvl w:val="2"/></w:pPr></w:style><w:style w:type="paragraph" w:styleId="Heading4"><w:name w:val="heading 4"/><w:aliases w:val="4numbers,H4,paragraphe[1],[req],-&gt;1.,4 dash,d,3,dash,Tempo Heading 4,THIRD,Description,Dash,description,Third,03 Dash,Titre 4,OdsKap4,h4,t4,titolo 4,a.,heading 4,Sottosottoparagrafo,p,AdaTitre1,ergo....,Heading 41,Heading 42,H41,H42"/><w:basedOn w:val="Normal"/><w:next w:val="Normal"/><w:qFormat/><w:pPr><w:numPr><w:ilvl w:val="3"/><w:numId w:val="2"/></w:numPr><w:spacing w:before="240"/><w:outlineLvl w:val="3"/></w:pPr></w:style><w:style w:type="paragraph" w:styleId="Heading5"><w:name w:val="heading 5"/><w:aliases w:val="Heading 5 - Mandatory requirements,H5,paragraphe[2],-&gt;a.,5 sub-bullet,sb,4,Ooh,Tempo Heading 5,h5,tit5,heading 5,Titolo 5 Carattere1,Titolo 5 Carattere Carattere,Heading 5 - Bad,Titre 5-Corps de texte,D Head,ergo.....,Mandatory reqmts"/><w:basedOn w:val="Normal"/><w:next w:val="Normal"/><w:qFormat/><w:pPr><w:numPr><w:ilvl w:val="4"/><w:numId w:val="2"/></w:numPr><w:spacing w:before="240"/><w:outlineLvl w:val="4"/></w:pPr></w:style><w:style w:type="paragraph" w:styleId="Heading6"><w:name w:val="heading 6"/><w:aliases w:val="hd6,h6,Appendix Titre 1,H6,paragraphe[3],Appendix - Titre 2,Appendix - titre 2,-&gt;1),Heading 6-Appendixes,Enum1,6,sub-dash,sd,heading 6,5,PROVA,Titre 6 - SC,H61,paragraphe[3]1,hd61,h61,Appendix Titre 11,heading 61,H62,paragraphe[3]2"/><w:basedOn w:val="Normal"/><w:next w:val="Normal"/><w:qFormat/><w:pPr><w:numPr><w:ilvl w:val="5"/><w:numId w:val="2"/></w:numPr><w:spacing w:before="240"/><w:outlineLvl w:val="5"/></w:pPr></w:style><w:style w:type="paragraph" w:styleId="Heading7"><w:name w:val="heading 7"/><w:aliases w:val="Appendix Titre 2,liste1,liste[1],-&gt;a),heading 7,h7,Appendix Titre 21,liste11,Heading 71,Appendix Titre 22,liste12,Heading 72,Appendix Titre 23,liste13,Heading 73,Appendix Titre 24,liste14,Heading 74,Appendix Titre 211,liste111,7,LauT7"/><w:basedOn w:val="Normal"/><w:next w:val="Normal"/><w:qFormat/><w:pPr><w:numPr><w:ilvl w:val="6"/><w:numId w:val="2"/></w:numPr><w:spacing w:before="240"/><w:outlineLvl w:val="6"/></w:pPr></w:style><w:style w:type="paragraph" w:styleId="Heading8"><w:name w:val="heading 8"/><w:aliases w:val="Appendix Titre 3,liste 2,liste[2],heading 8,Appendix Titre 31,liste 21,Heading 81,Appendix Titre 32,liste 22,Heading 82,Appendix Titre 33,liste 23,Heading 83,Appendix Titre 34,liste 24,Heading 84,Appendix Titre 311,liste 211,8,LauT8"/><w:basedOn w:val="Normal"/><w:next w:val="Normal"/><w:qFormat/><w:pPr><w:numPr><w:ilvl w:val="7"/><w:numId w:val="2"/></w:numPr><w:tabs><w:tab w:val="clear" w:pos="1440"/><w:tab w:val="num" w:pos="1560"/></w:tabs><w:spacing w:before="240"/><w:ind w:left="1560" w:hanging="1560"/><w:outlineLvl w:val="7"/></w:pPr></w:style><w:style w:type="paragraph" w:styleId="Heading9"><w:name w:val="heading 9"/><w:aliases w:val="Appendix Titre 4,liste[3],Titolo 10,App Heading,heading 9,Appendice,Appendice 9,Appendix Titre 41,Heading 91,Appendix Titre 42,Heading 92,Appendix Titre 43,Heading 93,Appendix Titre 44,Heading 94,Appendix Titre 411,Heading 911,9,LauT9"/><w:basedOn w:val="Normal"/><w:next w:val="Normal"/><w:qFormat/><w:pPr><w:numPr><w:ilvl w:val="8"/><w:numId w:val="2"/></w:numPr><w:tabs><w:tab w:val="clear" w:pos="1584"/><w:tab w:val="left" w:pos="1701"/></w:tabs><w:spacing w:before="240"/><w:ind w:left="1701" w:hanging="1701"/><w:outlineLvl w:val="8"/></w:pPr></w:style><w:style w:type="character" w:default="1" w:styleId="DefaultParagraphFont"><w:name w:val="Default Paragraph Font"/><w:semiHidden/></w:style><w:style w:type="table" w:default="1" w:styleId="TableNormal"><w:name w:val="Normal Table"/><w:semiHidden/><w:tblPr><w:tblInd w:w="0" w:type="dxa"/><w:tblCellMar><w:top w:w="0" w:type="dxa"/><w:left w:w="108" w:type="dxa"/><w:bottom w:w="0" w:type="dxa"/><w:right w:w="108" w:type="dxa"/></w:tblCellMar></w:tblPr></w:style><w:style w:type="numbering" w:default="1" w:styleId="NoList"><w:name w:val="No List"/><w:semiHidden/></w:style><w:style w:type="paragraph" w:customStyle="1" w:styleId="Text"><w:name w:val="Text"/><w:aliases w:val="titre2,titre1"/><w:basedOn w:val="Normal"/><w:pPr><w:spacing w:before="120"/></w:pPr></w:style><w:style w:type="paragraph" w:customStyle="1" w:styleId="Celtext"><w:name w:val="Cel:text"/><w:basedOn w:val="Normal"/><w:next w:val="Celtextcontinued"/><w:pPr><w:spacing w:before="60" w:after="60"/></w:pPr><w:rPr><w:snapToGrid w:val="0"/></w:rPr></w:style><w:style w:type="paragraph" w:customStyle="1" w:styleId="Celtextcontinued"><w:name w:val="Cel:text continued"/><w:basedOn w:val="Celtext"/><w:pPr><w:spacing w:before="0"/></w:pPr></w:style><w:style w:type="paragraph" w:customStyle="1" w:styleId="Celtitle"><w:name w:val="Cel:title"/><w:basedOn w:val="Normal"/><w:pPr><w:spacing w:before="60" w:after="60"/><w:jc w:val="center"/></w:pPr><w:rPr><w:b/><w:bCs/><w:snapToGrid w:val="0"/></w:rPr></w:style><w:style w:type="paragraph" w:styleId="Header"><w:name w:val="header"/><w:basedOn w:val="Normal"/><w:link w:val="HeaderChar"/><w:pPr><w:tabs><w:tab w:val="center" w:pos="4820"/><w:tab w:val="right" w:pos="9639"/></w:tabs></w:pPr><w:rPr><w:noProof/><w:sz w:val="18"/><w:szCs w:val="18"/></w:rPr></w:style><w:style w:type="paragraph" w:styleId="Footer"><w:name w:val="footer"/><w:basedOn w:val="Normal"/><w:link w:val="FooterChar"/><w:pPr><w:tabs><w:tab w:val="center" w:pos="4820"/><w:tab w:val="right" w:pos="9639"/></w:tabs></w:pPr><w:rPr><w:noProof/><w:sz w:val="16"/><w:szCs w:val="16"/></w:rPr></w:style><w:style w:type="paragraph" w:customStyle="1" w:styleId="Indent1"><w:name w:val="Indent 1"/><w:basedOn w:val="Normal"/><w:pPr><w:numPr><w:numId w:val="5"/></w:numPr><w:tabs><w:tab w:val="clear" w:pos="360"/><w:tab w:val="num" w:pos="284"/></w:tabs><w:spacing w:before="120"/></w:pPr></w:style><w:style w:type="paragraph" w:customStyle="1" w:styleId="Indent2"><w:name w:val="Indent 2"/><w:basedOn w:val="Normal"/><w:pPr><w:spacing w:before="120"/></w:pPr></w:style><w:style w:type="paragraph" w:customStyle="1" w:styleId="Indent1continued"><w:name w:val="Indent 1 continued"/><w:basedOn w:val="Indent1"/><w:pPr><w:numPr><w:numId w:val="0"/></w:numPr><w:spacing w:before="60"/><w:ind w:left="284"/></w:pPr></w:style><w:style w:type="paragraph" w:customStyle="1" w:styleId="Celindent"><w:name w:val="Cel:indent"/><w:basedOn w:val="Normal"/><w:pPr><w:numPr><w:numId w:val="3"/></w:numPr><w:tabs><w:tab w:val="clear" w:pos="360"/><w:tab w:val="num" w:pos="284"/></w:tabs><w:spacing w:after="60"/><w:jc w:val="left"/></w:pPr></w:style><w:style w:type="paragraph" w:styleId="NormalIndent"><w:name w:val="Normal Indent"/><w:basedOn w:val="Normal"/><w:next w:val="Normal"/><w:pPr><w:numPr><w:numId w:val="7"/></w:numPr><w:tabs><w:tab w:val="clear" w:pos="720"/><w:tab w:val="num" w:pos="284"/></w:tabs><w:spacing w:before="120"/><w:ind w:left="284" w:hanging="284"/></w:pPr><w:rPr><w:rFonts w:ascii="FuturaA Bk BT" w:hAnsi="FuturaA Bk BT" w:cs="Times New Roman"/><w:sz w:val="22"/><w:szCs w:val="22"/><w:lang w:eastAsia="en-US"/></w:rPr></w:style><w:style w:type="paragraph" w:customStyle="1" w:styleId="Figure"><w:name w:val="Figure"/><w:basedOn w:val="Normal"/><w:next w:val="Normal"/><w:pPr><w:keepNext/><w:spacing w:before="120" w:after="120"/><w:jc w:val="center"/></w:pPr><w:rPr><w:b/><w:bCs/></w:rPr></w:style><w:style w:type="paragraph" w:styleId="Index1"><w:name w:val="index 1"/><w:basedOn w:val="Normal"/><w:next w:val="Normal"/><w:autoRedefine/><w:semiHidden/><w:pPr><w:tabs><w:tab w:val="right" w:pos="4601"/></w:tabs><w:ind w:left="200" w:hanging="200"/><w:jc w:val="left"/></w:pPr><w:rPr><w:sz w:val="18"/><w:szCs w:val="18"/></w:rPr></w:style><w:style w:type="paragraph" w:styleId="Index2"><w:name w:val="index 2"/><w:basedOn w:val="Normal"/><w:next w:val="Normal"/><w:autoRedefine/><w:semiHidden/><w:pPr><w:tabs><w:tab w:val="right" w:pos="4601"/></w:tabs><w:ind w:left="400" w:hanging="200"/><w:jc w:val="left"/></w:pPr><w:rPr><w:sz w:val="18"/><w:szCs w:val="18"/></w:rPr></w:style><w:style w:type="paragraph" w:styleId="Index3"><w:name w:val="index 3"/><w:basedOn w:val="Normal"/><w:next w:val="Normal"/><w:autoRedefine/><w:semiHidden/><w:pPr><w:tabs><w:tab w:val="right" w:pos="4601"/></w:tabs><w:ind w:left="600" w:hanging="200"/><w:jc w:val="left"/></w:pPr><w:rPr><w:sz w:val="18"/><w:szCs w:val="18"/></w:rPr></w:style><w:style w:type="paragraph" w:styleId="Index4"><w:name w:val="index 4"/><w:basedOn w:val="Normal"/><w:next w:val="Normal"/><w:autoRedefine/><w:semiHidden/><w:pPr><w:tabs><w:tab w:val="right" w:pos="4601"/></w:tabs><w:ind w:left="800" w:hanging="200"/><w:jc w:val="left"/></w:pPr><w:rPr><w:sz w:val="18"/><w:szCs w:val="18"/></w:rPr></w:style><w:style w:type="paragraph" w:styleId="Index5"><w:name w:val="index 5"/><w:basedOn w:val="Normal"/><w:next w:val="Normal"/><w:autoRedefine/><w:semiHidden/><w:pPr><w:tabs><w:tab w:val="right" w:pos="4601"/></w:tabs><w:ind w:left="1000" w:hanging="200"/><w:jc w:val="left"/></w:pPr><w:rPr><w:sz w:val="18"/><w:szCs w:val="18"/></w:rPr></w:style><w:style w:type="paragraph" w:styleId="Index6"><w:name w:val="index 6"/><w:basedOn w:val="Normal"/><w:next w:val="Normal"/><w:autoRedefine/><w:semiHidden/><w:pPr><w:tabs><w:tab w:val="right" w:pos="4601"/></w:tabs><w:ind w:left="1200" w:hanging="200"/><w:jc w:val="left"/></w:pPr><w:rPr><w:sz w:val="18"/><w:szCs w:val="18"/></w:rPr></w:style><w:style w:type="paragraph" w:styleId="Index7"><w:name w:val="index 7"/><w:basedOn w:val="Normal"/><w:next w:val="Normal"/><w:autoRedefine/><w:semiHidden/><w:pPr><w:tabs><w:tab w:val="right" w:pos="4601"/></w:tabs><w:ind w:left="1400" w:hanging="200"/><w:jc w:val="left"/></w:pPr><w:rPr><w:sz w:val="18"/><w:szCs w:val="18"/></w:rPr></w:style><w:style w:type="paragraph" w:styleId="Index8"><w:name w:val="index 8"/><w:basedOn w:val="Normal"/><w:next w:val="Normal"/><w:autoRedefine/><w:semiHidden/><w:pPr><w:tabs><w:tab w:val="right" w:pos="4601"/></w:tabs><w:ind w:left="1600" w:hanging="200"/><w:jc w:val="left"/></w:pPr><w:rPr><w:sz w:val="18"/><w:szCs w:val="18"/></w:rPr></w:style><w:style w:type="paragraph" w:styleId="Index9"><w:name w:val="index 9"/><w:basedOn w:val="Normal"/><w:next w:val="Normal"/><w:autoRedefine/><w:semiHidden/><w:pPr><w:tabs><w:tab w:val="right" w:pos="4601"/></w:tabs><w:ind w:left="1800" w:hanging="200"/><w:jc w:val="left"/></w:pPr><w:rPr><w:sz w:val="18"/><w:szCs w:val="18"/></w:rPr></w:style><w:style w:type="paragraph" w:customStyle="1" w:styleId="CelluleCar"><w:name w:val="Cellule Car"/><w:basedOn w:val="Normal"/><w:pPr><w:spacing w:before="60" w:after="60"/><w:ind w:left="74"/><w:jc w:val="left"/></w:pPr><w:rPr><w:rFonts w:ascii="FuturaA Bk BT" w:hAnsi="FuturaA Bk BT" w:cs="Times New Roman"/></w:rPr></w:style><w:style w:type="paragraph" w:customStyle="1" w:styleId="Celindentcontinued"><w:name w:val="Cel:indent continued"/><w:basedOn w:val="Celindent"/><w:pPr><w:numPr><w:numId w:val="0"/></w:numPr><w:ind w:left="284"/></w:pPr></w:style><w:style w:type="paragraph" w:customStyle="1" w:styleId="Indent3"><w:name w:val="Indent 3"/><w:basedOn w:val="Indent2"/><w:pPr><w:numPr><w:numId w:val="6"/></w:numPr><w:tabs><w:tab w:val="clear" w:pos="360"/><w:tab w:val="num" w:pos="851"/></w:tabs><w:ind w:left="851"/></w:pPr></w:style><w:style w:type="paragraph" w:customStyle="1" w:styleId="Indent2continued"><w:name w:val="Indent 2 continued"/><w:basedOn w:val="Indent2"/><w:pPr><w:spacing w:before="60"/><w:ind w:left="567"/></w:pPr></w:style><w:style w:type="paragraph" w:customStyle="1" w:styleId="Indent3continued"><w:name w:val="Indent 3 continued"/><w:basedOn w:val="Indent2continued"/><w:pPr><w:ind w:left="851"/></w:pPr></w:style><w:style w:type="paragraph" w:customStyle="1" w:styleId="PageDeGardeAlstomLogo"><w:name w:val="PageDeGarde:Alstom Logo"/><w:basedOn w:val="Normal"/><w:pPr><w:spacing w:after="240"/><w:jc w:val="center"/></w:pPr><w:rPr><w:color w:val="000080"/></w:rPr></w:style><w:style w:type="paragraph" w:customStyle="1" w:styleId="PageDeGardeAlstomUnit"><w:name w:val="PageDeGarde:Alstom Unit"/><w:basedOn w:val="PageDeGardeAlstomLogo"/><w:pPr><w:spacing w:after="120"/></w:pPr><w:rPr><w:b/><w:bCs/><w:sz w:val="28"/><w:szCs w:val="28"/></w:rPr></w:style><w:style w:type="paragraph" w:customStyle="1" w:styleId="PageDeGardeAlstomsite"><w:name w:val="PageDeGarde:Alstom site"/><w:basedOn w:val="PageDeGardeAlstomLogo"/><w:pPr><w:spacing w:after="720"/></w:pPr><w:rPr><w:b/><w:bCs/><w:spacing w:val="20"/></w:rPr></w:style><w:style w:type="paragraph" w:styleId="TOC1"><w:name w:val="toc 1"/><w:basedOn w:val="Normal"/><w:uiPriority w:val="39"/><w:qFormat/><w:pPr><w:tabs><w:tab w:val="left" w:pos="397"/><w:tab w:val="right" w:leader="dot" w:pos="9922"/></w:tabs><w:spacing w:before="120"/><w:ind w:left="397" w:right="567" w:hanging="397"/></w:pPr><w:rPr><w:b/><w:bCs/><w:caps/><w:noProof/><w:sz w:val="18"/><w:szCs w:val="18"/></w:rPr></w:style><w:style w:type="paragraph" w:styleId="TOC2"><w:name w:val="toc 2"/><w:basedOn w:val="Normal"/><w:uiPriority w:val="39"/><w:qFormat/><w:pPr><w:tabs><w:tab w:val="left" w:pos="800"/><w:tab w:val="left" w:pos="993"/><w:tab w:val="right" w:leader="dot" w:pos="9922"/></w:tabs><w:ind w:left="595" w:right="567" w:hanging="397"/></w:pPr><w:rPr><w:b/><w:bCs/><w:caps/><w:noProof/><w:sz w:val="16"/><w:szCs w:val="16"/></w:rPr></w:style><w:style w:type="paragraph" w:styleId="TOC3"><w:name w:val="toc 3"/><w:basedOn w:val="Normal"/><w:uiPriority w:val="39"/><w:qFormat/><w:pPr><w:tabs><w:tab w:val="left" w:pos="993"/><w:tab w:val="left" w:pos="1202"/><w:tab w:val="right" w:leader="dot" w:pos="9922"/></w:tabs><w:ind w:left="993" w:right="567" w:hanging="590"/></w:pPr><w:rPr><w:caps/><w:noProof/><w:sz w:val="16"/><w:szCs w:val="16"/></w:rPr></w:style><w:style w:type="paragraph" w:styleId="TOC4"><w:name w:val="toc 4"/><w:basedOn w:val="Normal"/><w:uiPriority w:val="39"/><w:pPr><w:tabs><w:tab w:val="left" w:pos="1599"/><w:tab w:val="right" w:leader="dot" w:pos="9922"/></w:tabs><w:ind w:left="998" w:right="567" w:hanging="397"/></w:pPr><w:rPr><w:noProof/><w:sz w:val="18"/><w:szCs w:val="18"/></w:rPr></w:style><w:style w:type="paragraph" w:styleId="TOC5"><w:name w:val="toc 5"/><w:basedOn w:val="Heading5"/><w:next w:val="Normal"/><w:semiHidden/><w:pPr><w:keepNext/><w:numPr><w:ilvl w:val="0"/><w:numId w:val="0"/></w:numPr><w:tabs><w:tab w:val="left" w:pos="1985"/><w:tab w:val="right" w:leader="dot" w:pos="9922"/></w:tabs><w:spacing w:before="0"/><w:ind w:left="799"/><w:outlineLvl w:val="9"/></w:pPr><w:rPr><w:sz w:val="22"/><w:szCs w:val="22"/><w:lang w:val="fr-FR"/></w:rPr></w:style><w:style w:type="paragraph" w:styleId="TOC6"><w:name w:val="toc 6"/><w:basedOn w:val="Heading6"/><w:semiHidden/><w:pPr><w:keepNext/><w:tabs><w:tab w:val="clear" w:pos="425"/><w:tab w:val="right" w:leader="dot" w:pos="9922"/></w:tabs><w:spacing w:before="0"/><w:ind w:left="998" w:firstLine="0"/><w:outlineLvl w:val="9"/></w:pPr><w:rPr><w:sz w:val="18"/><w:szCs w:val="18"/><w:lang w:val="fr-FR"/></w:rPr></w:style><w:style w:type="paragraph" w:styleId="TOC7"><w:name w:val="toc 7"/><w:basedOn w:val="Heading7"/><w:semiHidden/><w:pPr><w:keepNext/><w:tabs><w:tab w:val="clear" w:pos="425"/><w:tab w:val="right" w:leader="dot" w:pos="9922"/></w:tabs><w:spacing w:before="0"/><w:ind w:left="1202" w:firstLine="0"/><w:outlineLvl w:val="9"/></w:pPr><w:rPr><w:sz w:val="22"/><w:szCs w:val="22"/><w:lang w:val="fr-FR"/></w:rPr></w:style><w:style w:type="paragraph" w:styleId="TOC8"><w:name w:val="toc 8"/><w:basedOn w:val="Heading8"/><w:semiHidden/><w:pPr><w:keepNext/><w:tabs><w:tab w:val="clear" w:pos="425"/><w:tab w:val="right" w:leader="dot" w:pos="9922"/></w:tabs><w:spacing w:before="0"/><w:ind w:left="1400" w:firstLine="0"/><w:outlineLvl w:val="9"/></w:pPr><w:rPr><w:sz w:val="22"/><w:szCs w:val="22"/><w:lang w:val="fr-FR"/></w:rPr></w:style><w:style w:type="paragraph" w:styleId="TOC9"><w:name w:val="toc 9"/><w:basedOn w:val="Heading9"/><w:semiHidden/><w:pPr><w:keepNext/><w:tabs><w:tab w:val="clear" w:pos="425"/><w:tab w:val="clear" w:pos="1701"/><w:tab w:val="right" w:leader="dot" w:pos="9922"/></w:tabs><w:spacing w:before="0"/><w:ind w:left="1599" w:firstLine="0"/><w:outlineLvl w:val="9"/></w:pPr><w:rPr><w:sz w:val="22"/><w:szCs w:val="22"/><w:lang w:val="fr-FR"/></w:rPr></w:style><w:style w:type="paragraph" w:styleId="IndexHeading"><w:name w:val="index heading"/><w:basedOn w:val="Normal"/><w:next w:val="Index1"/><w:semiHidden/><w:pPr><w:pBdr><w:top w:val="single" w:sz="12" w:space="0" w:color="auto"/></w:pBdr><w:spacing w:before="360" w:after="240"/><w:jc w:val="left"/></w:pPr><w:rPr><w:b/><w:bCs/><w:i/><w:iCs/><w:sz w:val="26"/><w:szCs w:val="26"/></w:rPr></w:style><w:style w:type="paragraph" w:customStyle="1" w:styleId="RevisionsContents"><w:name w:val="Revisions / Contents"/><w:basedOn w:val="Normal"/><w:pPr><w:spacing w:before="480" w:after="240"/><w:jc w:val="center"/></w:pPr><w:rPr><w:b/><w:bCs/><w:spacing w:val="40"/><w:sz w:val="28"/><w:szCs w:val="28"/></w:rPr></w:style><w:style w:type="character" w:customStyle="1" w:styleId="motdefini"><w:name w:val="mot defini"/><w:rPr><w:rFonts w:cs="Times New Roman"/><w:b/><w:bCs/><w:i/><w:iCs/></w:rPr></w:style><w:style w:type="paragraph" w:customStyle="1" w:styleId="Celluleretrait"><w:name w:val="Cellule retrait"/><w:basedOn w:val="CelluleCar"/><w:pPr><w:numPr><w:numId w:val="153"/></w:numPr></w:pPr></w:style><w:style w:type="character" w:customStyle="1" w:styleId="PageDeGarde"><w:name w:val="PageDeGarde"/><w:rPr><w:rFonts w:ascii="FuturaA Bk BT" w:hAnsi="FuturaA Bk BT"/><w:noProof/></w:rPr></w:style><w:style w:type="character" w:customStyle="1" w:styleId="PageEvolution"><w:name w:val="PageEvolution"/><w:rPr><w:noProof/><w:spacing w:val="0"/><w:kern w:val="0"/><w:position w:val="0"/><w:vertAlign w:val="baseline"/></w:rPr></w:style><w:style w:type="paragraph" w:customStyle="1" w:styleId="Celluletitre"><w:name w:val="Cellule titre"/><w:basedOn w:val="CelluleCar"/><w:pPr><w:ind w:left="0"/><w:jc w:val="center"/></w:pPr><w:rPr><w:b/><w:bCs/><w:sz w:val="22"/><w:szCs w:val="22"/></w:rPr></w:style><w:style w:type="paragraph" w:customStyle="1" w:styleId="Retrait2normal"><w:name w:val="Retrait 2 normal"/><w:basedOn w:val="NormalIndent"/><w:pPr><w:numPr><w:numId w:val="8"/></w:numPr><w:tabs><w:tab w:val="clear" w:pos="720"/><w:tab w:val="num" w:pos="851"/></w:tabs><w:ind w:left="851" w:hanging="284"/></w:pPr></w:style><w:style w:type="paragraph" w:customStyle="1" w:styleId="Cellule"><w:name w:val="Cellule"/><w:basedOn w:val="Normal"/><w:pPr><w:spacing w:before="60" w:after="60"/><w:ind w:left="74"/><w:jc w:val="left"/></w:pPr><w:rPr><w:rFonts w:ascii="FuturaA Bk BT" w:hAnsi="FuturaA Bk BT" w:cs="Times New Roman"/></w:rPr></w:style><w:style w:type="character" w:customStyle="1" w:styleId="CelluleretraitCar"><w:name w:val="Cellule retrait Car"/><w:rPr><w:rFonts w:ascii="FuturaA Bk BT" w:hAnsi="FuturaA Bk BT" w:cs="TimesNewRomanMT Cond"/><w:noProof w:val="0"/><w:sz w:val="18"/><w:szCs w:val="18"/><w:lang w:val="en-GB" w:eastAsia="fr-FR" w:bidi="ar-SA"/></w:rPr></w:style><w:style w:type="character" w:styleId="Hyperlink"><w:name w:val="Hyperlink"/><w:uiPriority w:val="99"/><w:rPr><w:color w:val="0000FF"/><w:u w:val="single"/></w:rPr></w:style><w:style w:type="character" w:customStyle="1" w:styleId="Indent1Car"><w:name w:val="Indent 1 Car"/><w:rPr><w:rFonts w:ascii="Arial" w:hAnsi="Arial" w:cs="Arial"/><w:lang w:val="en-GB" w:eastAsia="fr-FR" w:bidi="ar-SA"/></w:rPr></w:style><w:style w:type="paragraph" w:customStyle="1" w:styleId="Texte"><w:name w:val="Texte"/><w:basedOn w:val="Normal"/><w:pPr><w:spacing w:before="120"/></w:pPr><w:rPr><w:rFonts w:ascii="FuturaA Bk BT" w:hAnsi="FuturaA Bk BT" w:cs="Times"/></w:rPr></w:style><w:style w:type="character" w:customStyle="1" w:styleId="TexteCar"><w:name w:val="Texte Car"/><w:rPr><w:rFonts w:ascii="FuturaA Bk BT" w:hAnsi="FuturaA Bk BT" w:cs="Times"/><w:lang w:val="en-GB" w:eastAsia="fr-FR" w:bidi="ar-SA"/></w:rPr></w:style><w:style w:type="paragraph" w:customStyle="1" w:styleId="DocApplicable"><w:name w:val="DocApplicable"/><w:basedOn w:val="Normal"/><w:pPr><w:numPr><w:numId w:val="9"/></w:numPr><w:tabs><w:tab w:val="left" w:pos="567"/><w:tab w:val="left" w:pos="2552"/></w:tabs><w:spacing w:before="120"/><w:jc w:val="left"/></w:pPr><w:rPr><w:rFonts w:ascii="FuturaA Bk BT" w:hAnsi="FuturaA Bk BT" w:cs="Times"/><w:snapToGrid w:val="0"/><w:color w:val="000000"/></w:rPr></w:style><w:style w:type="paragraph" w:styleId="BodyText"><w:name w:val="Body Text"/><w:basedOn w:val="Normal"/><w:pPr><w:tabs><w:tab w:val="left" w:pos="0"/><w:tab w:val="left" w:pos="851"/><w:tab w:val="left" w:pos="5670"/><w:tab w:val="left" w:pos="6096"/></w:tabs><w:spacing w:before="40" w:after="40"/><w:jc w:val="left"/></w:pPr><w:rPr><w:i/><w:iCs/><w:sz w:val="16"/><w:szCs w:val="16"/></w:rPr></w:style><w:style w:type="paragraph" w:customStyle="1" w:styleId="InputOutput"><w:name w:val="Input Output"/><w:basedOn w:val="Normal"/><w:pPr><w:numPr><w:numId w:val="10"/></w:numPr><w:tabs><w:tab w:val="clear" w:pos="360"/><w:tab w:val="num" w:pos="284"/><w:tab w:val="left" w:pos="1701"/></w:tabs><w:spacing w:before="120"/><w:jc w:val="left"/></w:pPr><w:rPr><w:rFonts w:ascii="FuturaA Bk BT" w:hAnsi="FuturaA Bk BT" w:cs="Times"/><w:sz w:val="22"/></w:rPr></w:style><w:style w:type="paragraph" w:customStyle="1" w:styleId="NotetoAuthortextCarCar"><w:name w:val="Note to Author:text Car Car"/><w:basedOn w:val="Normal"/><w:pPr><w:pBdr><w:top w:val="single" w:sz="4" w:space="1" w:color="auto" w:shadow="1"/><w:left w:val="single" w:sz="4" w:space="4" w:color="auto" w:shadow="1"/><w:bottom w:val="single" w:sz="4" w:space="1" w:color="auto" w:shadow="1"/><w:right w:val="single" w:sz="4" w:space="4" w:color="auto" w:shadow="1"/></w:pBdr><w:shd w:val="clear" w:color="auto" w:fill="FFFF00"/><w:spacing w:before="60"/></w:pPr></w:style><w:style w:type="character" w:styleId="LineNumber"><w:name w:val="line number"/><w:basedOn w:val="DefaultParagraphFont"/></w:style><w:style w:type="paragraph" w:customStyle="1" w:styleId="NotetoAuthortitle"><w:name w:val="Note to Author:title"/><w:basedOn w:val="Text"/><w:next w:val="Normal"/><w:pPr><w:pBdr><w:top w:val="single" w:sz="4" w:space="1" w:color="auto" w:shadow="1"/><w:left w:val="single" w:sz="4" w:space="4" w:color="auto" w:shadow="1"/><w:bottom w:val="single" w:sz="4" w:space="1" w:color="auto" w:shadow="1"/><w:right w:val="single" w:sz="4" w:space="4" w:color="auto" w:shadow="1"/></w:pBdr><w:shd w:val="clear" w:color="auto" w:fill="FFFF00"/><w:spacing w:before="240"/></w:pPr><w:rPr><w:rFonts w:cs="Times New Roman"/><w:b/><w:bCs/><w:u w:val="single"/></w:rPr></w:style><w:style w:type="character" w:customStyle="1" w:styleId="NotetoAuthortextCarCarCar"><w:name w:val="Note to Author:text Car Car Car"/><w:rPr><w:rFonts w:ascii="FuturaA Bk BT" w:hAnsi="FuturaA Bk BT" w:cs="Helvetica"/><w:lang w:val="en-GB" w:eastAsia="fr-FR" w:bidi="ar-SA"/></w:rPr></w:style><w:style w:type="paragraph" w:customStyle="1" w:styleId="NotetoAuthortext"><w:name w:val="Note to Author:text"/><w:basedOn w:val="Normal"/><w:pPr><w:pBdr><w:top w:val="single" w:sz="4" w:space="1" w:color="auto" w:shadow="1"/><w:left w:val="single" w:sz="4" w:space="4" w:color="auto" w:shadow="1"/><w:bottom w:val="single" w:sz="4" w:space="1" w:color="auto" w:shadow="1"/><w:right w:val="single" w:sz="4" w:space="4" w:color="auto" w:shadow="1"/></w:pBdr><w:shd w:val="clear" w:color="auto" w:fill="FFFF00"/><w:spacing w:before="60"/></w:pPr><w:rPr><w:rFonts w:cs="Times New Roman"/></w:rPr></w:style><w:style w:type="paragraph" w:customStyle="1" w:styleId="NotetoAuthorindent"><w:name w:val="Note to Author:indent"/><w:basedOn w:val="Indent1"/><w:pPr><w:numPr><w:numId w:val="4"/></w:numPr><w:pBdr><w:top w:val="single" w:sz="4" w:space="1" w:color="auto" w:shadow="1"/><w:left w:val="single" w:sz="4" w:space="4" w:color="auto" w:shadow="1"/><w:bottom w:val="single" w:sz="4" w:space="1" w:color="auto" w:shadow="1"/><w:right w:val="single" w:sz="4" w:space="4" w:color="auto" w:shadow="1"/></w:pBdr><w:shd w:val="clear" w:color="auto" w:fill="FFFF00"/></w:pPr><w:rPr><w:rFonts w:cs="Times New Roman"/></w:rPr></w:style><w:style w:type="paragraph" w:styleId="BalloonText"><w:name w:val="Balloon Text"/><w:basedOn w:val="Normal"/><w:semiHidden/><w:rPr><w:rFonts w:ascii="Tahoma" w:hAnsi="Tahoma" w:cs="Tahoma"/><w:sz w:val="16"/><w:szCs w:val="16"/></w:rPr></w:style><w:style w:type="character" w:styleId="CommentReference"><w:name w:val="annotation reference"/><w:semiHidden/><w:rPr><w:sz w:val="16"/><w:szCs w:val="16"/></w:rPr></w:style><w:style w:type="paragraph" w:styleId="CommentText"><w:name w:val="annotation text"/><w:basedOn w:val="Normal"/><w:semiHidden/></w:style><w:style w:type="paragraph" w:styleId="CommentSubject"><w:name w:val="annotation subject"/><w:basedOn w:val="CommentText"/><w:next w:val="CommentText"/><w:semiHidden/><w:rPr><w:b/><w:bCs/></w:rPr></w:style><w:style w:type="character" w:styleId="FollowedHyperlink"><w:name w:val="FollowedHyperlink"/><w:rPr><w:color w:val="800080"/><w:u w:val="single"/></w:rPr></w:style><w:style w:type="paragraph" w:customStyle="1" w:styleId="DocReference"><w:name w:val="DocReference"/><w:basedOn w:val="Normal"/><w:pPr><w:numPr><w:numId w:val="11"/></w:numPr><w:spacing w:before="120"/><w:jc w:val="left"/></w:pPr><w:rPr><w:color w:val="000000"/></w:rPr></w:style><w:style w:type="paragraph" w:styleId="TableofFigures"><w:name w:val="table of figures"/><w:basedOn w:val="Normal"/><w:next w:val="Normal"/><w:uiPriority w:val="99"/><w:unhideWhenUsed/><w:rsid w:val="00AC2A69"/></w:style><w:style w:type="paragraph" w:styleId="TOCHeading"><w:name w:val="TOC Heading"/><w:basedOn w:val="Heading1"/><w:next w:val="Normal"/><w:uiPriority w:val="39"/><w:unhideWhenUsed/><w:qFormat/><w:rsid w:val="00AC2A69"/><w:pPr><w:keepNext/><w:keepLines/><w:widowControl/><w:numPr><w:numId w:val="0"/></w:numPr><w:spacing w:before="480" w:line="276" w:lineRule="auto"/><w:outlineLvl w:val="9"/></w:pPr><w:rPr><w:rFonts w:ascii="Cambria" w:hAnsi="Cambria" w:cs="Times New Roman"/><w:caps w:val="0"/><w:color w:val="365F91"/><w:sz w:val="28"/><w:szCs w:val="28"/></w:rPr></w:style><w:style w:type="paragraph" w:customStyle="1" w:styleId="ReferenceDoc"><w:name w:val="ReferenceDoc"/><w:basedOn w:val="Normal"/><w:rsid w:val="004F49C4"/><w:pPr><w:tabs><w:tab w:val="num" w:pos="360"/><w:tab w:val="right" w:pos="9860"/></w:tabs><w:spacing w:after="120"/><w:jc w:val="left"/></w:pPr><w:rPr><w:rFonts w:ascii="Arial" w:hAnsi="Arial" w:cs="Times New Roman"/><w:lang w:val="en-GB" w:eastAsia="en-US"/></w:rPr></w:style><w:style w:type="paragraph" w:customStyle="1" w:styleId="ReqProperties"><w:name w:val="Req_Properties"/><w:basedOn w:val="Normal"/><w:rsid w:val="004F49C4"/><w:pPr><w:jc w:val="left"/></w:pPr><w:rPr><w:rFonts w:ascii="FuturaA Bk BT" w:hAnsi="FuturaA Bk BT" w:cs="Times New Roman"/><w:color w:val="808000"/><w:sz w:val="16"/><w:szCs w:val="24"/><w:lang w:val="en-GB" w:eastAsia="fr-FR"/></w:rPr></w:style><w:style w:type="paragraph" w:styleId="Caption"><w:name w:val="caption"/><w:aliases w:val="Caption2,Légende_Figure,Char1,Legend_Figures,figure,Caption2 Carattere Carattere Carattere Carattere Carattere Carattere,Caption2 Carattere Carattere"/><w:basedOn w:val="Normal"/><w:next w:val="Normal"/><w:unhideWhenUsed/><w:qFormat/><w:rsid w:val="00F0457D"/><w:pPr><w:spacing w:before="120" w:after="120"/><w:jc w:val="center"/></w:pPr><w:rPr><w:b/><w:bCs/></w:rPr></w:style><w:style w:type="paragraph" w:styleId="BodyTextIndent3"><w:name w:val="Body Text Indent 3"/><w:basedOn w:val="Normal"/><w:link w:val="BodyTextIndent3Char"/><w:semiHidden/><w:unhideWhenUsed/><w:rsid w:val="00CE438E"/><w:pPr><w:spacing w:after="120"/><w:ind w:left="283"/></w:pPr><w:rPr><w:sz w:val="16"/><w:szCs w:val="16"/></w:rPr></w:style><w:style w:type="character" w:customStyle="1" w:styleId="BodyTextIndent3Char"><w:name w:val="Body Text Indent 3 Char"/><w:link w:val="BodyTextIndent3"/><w:uiPriority w:val="99"/><w:semiHidden/><w:rsid w:val="00CE438E"/><w:rPr><w:sz w:val="16"/><w:szCs w:val="16"/><w:lang w:eastAsia="it-IT"/></w:rPr></w:style><w:style w:type="paragraph" w:customStyle="1" w:styleId="Scrivente"><w:name w:val="Scrivente"/><w:basedOn w:val="Normal"/><w:rsid w:val="00CE438E"/><w:pPr><w:framePr w:hSpace="256" w:vSpace="256" w:wrap="auto" w:vAnchor="page" w:hAnchor="margin" w:y="886"/><w:tabs><w:tab w:val="center" w:pos="4819"/><w:tab w:val="right" w:pos="9639"/></w:tabs><w:spacing w:before="74" w:after="60"/></w:pPr><w:rPr><w:rFonts w:ascii="Times New Roman" w:hAnsi="Times New Roman" w:cs="Times New Roman"/><w:i/><w:sz w:val="24"/></w:rPr></w:style><w:style w:type="character" w:customStyle="1" w:styleId="FooterChar"><w:name w:val="Footer Char"/><w:link w:val="Footer"/><w:uiPriority w:val="99"/><w:rsid w:val="00CE438E"/><w:rPr><w:noProof/><w:sz w:val="16"/><w:szCs w:val="16"/><w:lang w:eastAsia="it-IT"/></w:rPr></w:style><w:style w:type="character" w:customStyle="1" w:styleId="HeaderChar"><w:name w:val="Header Char"/><w:link w:val="Header"/><w:rsid w:val="00B813BE"/><w:rPr><w:noProof/><w:sz w:val="18"/><w:szCs w:val="18"/><w:lang w:eastAsia="it-IT"/></w:rPr></w:style><w:style w:type="table" w:styleId="TableGrid"><w:name w:val="Table Grid"/><w:basedOn w:val="TableNormal"/><w:rsid w:val="00F824A0"/><w:rPr><w:rFonts w:ascii="Times New Roman" w:hAnsi="Times New Roman" w:cs="Times New Roman"/><w:lang w:val="fr-FR" w:eastAsia="fr-FR"/></w:rPr><w:tblPr><w:tblBorders><w:top w:val="single" w:sz="4" w:space="0" w:color="auto"/><w:left w:val="single" w:sz="4" w:space="0" w:color="auto"/><w:bottom w:val="single" w:sz="4" w:space="0" w:color="auto"/><w:right w:val="single" w:sz="4" w:space="0" w:color="auto"/><w:insideH w:val="single" w:sz="4" w:space="0" w:color="auto"/><w:insideV w:val="single" w:sz="4" w:space="0" w:color="auto"/></w:tblBorders></w:tblPr></w:style><w:style w:type="paragraph" w:styleId="FootnoteText"><w:name w:val="footnote text"/><w:basedOn w:val="Normal"/><w:link w:val="FootnoteTextChar"/><w:uiPriority w:val="99"/><w:semiHidden/><w:unhideWhenUsed/><w:rsid w:val="00FF26EE"/></w:style><w:style w:type="character" w:customStyle="1" w:styleId="FootnoteTextChar"><w:name w:val="Footnote Text Char"/><w:basedOn w:val="DefaultParagraphFont"/><w:link w:val="FootnoteText"/><w:uiPriority w:val="99"/><w:semiHidden/><w:rsid w:val="00FF26EE"/></w:style><w:style w:type="character" w:styleId="FootnoteReference"><w:name w:val="footnote reference"/><w:semiHidden/><w:rsid w:val="00FF26EE"/><w:rPr><w:vertAlign w:val="superscript"/></w:rPr></w:style><w:style w:type="paragraph" w:customStyle="1" w:styleId="Numberslevel1"><w:name w:val="Numbers level 1"/><w:basedOn w:val="Normal"/><w:autoRedefine/><w:rsid w:val="00FF26EE"/><w:pPr><w:numPr><w:numId w:val="13"/></w:numPr><w:jc w:val="center"/></w:pPr><w:rPr><w:rFonts w:cs="Times New Roman"/><w:sz w:val="24"/><w:szCs w:val="24"/><w:lang w:val="en-GB" w:eastAsia="fr-FR"/></w:rPr></w:style><w:style w:type="paragraph" w:customStyle="1" w:styleId="Exampletitle"><w:name w:val="Example:title"/><w:basedOn w:val="Normal"/><w:next w:val="Normal"/><w:rsid w:val="00E40CDB"/><w:pPr><w:pBdr><w:top w:val="single" w:sz="4" w:space="1" w:color="auto" w:shadow="1"/><w:left w:val="single" w:sz="4" w:space="4" w:color="auto" w:shadow="1"/><w:bottom w:val="single" w:sz="4" w:space="0" w:color="auto" w:shadow="1"/><w:right w:val="single" w:sz="4" w:space="4" w:color="auto" w:shadow="1"/></w:pBdr><w:shd w:val="pct20" w:color="auto" w:fill="FFFFFF"/><w:spacing w:before="240"/></w:pPr><w:rPr><w:rFonts w:ascii="FuturaA Bk BT" w:hAnsi="FuturaA Bk BT" w:cs="Times New Roman"/><w:b/><w:bCs/><w:u w:val="single"/><w:lang w:val="en-GB" w:eastAsia="fr-FR"/></w:rPr></w:style><w:style w:type="table" w:customStyle="1" w:styleId="Grigliachiara-Colore41"><w:name w:val="Griglia chiara - Colore 41"/><w:basedOn w:val="TableNormal"/><w:next w:val="LightGrid-Accent4"/><w:uiPriority w:val="62"/><w:rsid w:val="0013494A"/><w:rPr><w:rFonts w:ascii="Times New Roman" w:hAnsi="Times New Roman" w:cs="Times New Roman"/><w:lang w:val="fr-FR" w:eastAsia="fr-FR"/></w:rPr><w:tblPr><w:tblStyleRowBandSize w:val="1"/><w:tblStyleColBandSize w:val="1"/><w:tblBorders><w:top w:val="single" w:sz="8" w:space="0" w:color="8064A2"/><w:left w:val="single" w:sz="8" w:space="0" w:color="8064A2"/><w:bottom w:val="single" w:sz="8" w:space="0" w:color="8064A2"/><w:right w:val="single" w:sz="8" w:space="0" w:color="8064A2"/><w:insideH w:val="single" w:sz="8" w:space="0" w:color="8064A2"/><w:insideV w:val="single" w:sz="8" w:space="0" w:color="8064A2"/></w:tblBorders></w:tblPr><w:tblStylePr w:type="firstRow"><w:pPr><w:spacing w:before="0" w:after="0" w:line="240" w:lineRule="auto"/></w:pPr><w:rPr><w:rFonts w:ascii="DengXian" w:eastAsia="Times New Roman" w:hAnsi="DengXian" w:cs="Times New Roman"/><w:b/><w:bCs/></w:rPr><w:tblPr/><w:tcPr><w:tcBorders><w:top w:val="single" w:sz="8" w:space="0" w:color="8064A2"/><w:left w:val="single" w:sz="8" w:space="0" w:color="8064A2"/><w:bottom w:val="single" w:sz="18" w:space="0" w:color="8064A2"/><w:right w:val="single" w:sz="8" w:space="0" w:color="8064A2"/><w:insideH w:val="nil"/><w:insideV w:val="single" w:sz="8" w:space="0" w:color="8064A2"/></w:tcBorders></w:tcPr></w:tblStylePr><w:tblStylePr w:type="lastRow"><w:pPr><w:spacing w:before="0" w:after="0" w:line="240" w:lineRule="auto"/></w:pPr><w:rPr><w:rFonts w:ascii="DengXian" w:eastAsia="Times New Roman" w:hAnsi="DengXian" w:cs="Times New Roman"/><w:b/><w:bCs/></w:rPr><w:tblPr/><w:tcPr><w:tcBorders><w:top w:val="double" w:sz="6" w:space="0" w:color="8064A2"/><w:left w:val="single" w:sz="8" w:space="0" w:color="8064A2"/><w:bottom w:val="single" w:sz="8" w:space="0" w:color="8064A2"/><w:right w:val="single" w:sz="8" w:space="0" w:color="8064A2"/><w:insideH w:val="nil"/><w:insideV w:val="single" w:sz="8" w:space="0" w:color="8064A2"/></w:tcBorders></w:tcPr></w:tblStylePr><w:tblStylePr w:type="firstCol"><w:rPr><w:rFonts w:ascii="DengXian" w:eastAsia="Times New Roman" w:hAnsi="DengXian" w:cs="Times New Roman"/><w:b/><w:bCs/></w:rPr></w:tblStylePr><w:tblStylePr w:type="lastCol"><w:rPr><w:rFonts w:ascii="DengXian" w:eastAsia="Times New Roman" w:hAnsi="DengXian" w:cs="Times New Roman"/><w:b/><w:bCs/></w:rPr><w:tblPr/><w:tcPr><w:tcBorders><w:top w:val="single" w:sz="8" w:space="0" w:color="8064A2"/><w:left w:val="single" w:sz="8" w:space="0" w:color="8064A2"/><w:bottom w:val="single" w:sz="8" w:space="0" w:color="8064A2"/><w:right w:val="single" w:sz="8" w:space="0" w:color="8064A2"/></w:tcBorders></w:tcPr></w:tblStylePr><w:tblStylePr w:type="band1Vert"><w:tblPr/><w:tcPr><w:tcBorders><w:top w:val="single" w:sz="8" w:space="0" w:color="8064A2"/><w:left w:val="single" w:sz="8" w:space="0" w:color="8064A2"/><w:bottom w:val="single" w:sz="8" w:space="0" w:color="8064A2"/><w:right w:val="single" w:sz="8" w:space="0" w:color="8064A2"/></w:tcBorders><w:shd w:val="clear" w:color="auto" w:fill="DFD8E8"/></w:tcPr></w:tblStylePr><w:tblStylePr w:type="band1Horz"><w:tblPr/><w:tcPr><w:tcBorders><w:top w:val="single" w:sz="8" w:space="0" w:color="8064A2"/><w:left w:val="single" w:sz="8" w:space="0" w:color="8064A2"/><w:bottom w:val="single" w:sz="8" w:space="0" w:color="8064A2"/><w:right w:val="single" w:sz="8" w:space="0" w:color="8064A2"/><w:insideV w:val="single" w:sz="8" w:space="0" w:color="8064A2"/></w:tcBorders><w:shd w:val="clear" w:color="auto" w:fill="DFD8E8"/></w:tcPr></w:tblStylePr><w:tblStylePr w:type="band2Horz"><w:tblPr/><w:tcPr><w:tcBorders><w:top w:val="single" w:sz="8" w:space="0" w:color="8064A2"/><w:left w:val="single" w:sz="8" w:space="0" w:color="8064A2"/><w:bottom w:val="single" w:sz="8" w:space="0" w:color="8064A2"/><w:right w:val="single" w:sz="8" w:space="0" w:color="8064A2"/><w:insideV w:val="single" w:sz="8" w:space="0" w:color="8064A2"/></w:tcBorders></w:tcPr></w:tblStylePr></w:style><w:style w:type="table" w:styleId="LightGrid-Accent4"><w:name w:val="Light Grid Accent 4"/><w:basedOn w:val="TableNormal"/><w:uiPriority w:val="62"/><w:rsid w:val="0013494A"/><w:tblPr><w:tblStyleRowBandSize w:val="1"/><w:tblStyleColBandSize w:val="1"/><w:tblBorders><w:top w:val="single" w:sz="8" w:space="0" w:color="8064A2"/><w:left w:val="single" w:sz="8" w:space="0" w:color="8064A2"/><w:bottom w:val="single" w:sz="8" w:space="0" w:color="8064A2"/><w:right w:val="single" w:sz="8" w:space="0" w:color="8064A2"/><w:insideH w:val="single" w:sz="8" w:space="0" w:color="8064A2"/><w:insideV w:val="single" w:sz="8" w:space="0" w:color="8064A2"/></w:tblBorders></w:tblPr><w:tblStylePr w:type="firstRow"><w:pPr><w:spacing w:before="0" w:after="0" w:line="240" w:lineRule="auto"/></w:pPr><w:rPr><w:rFonts w:ascii="DengXian" w:eastAsia="Times New Roman" w:hAnsi="DengXian" w:cs="Times New Roman"/><w:b/><w:bCs/></w:rPr><w:tblPr/><w:tcPr><w:tcBorders><w:top w:val="single" w:sz="8" w:space="0" w:color="8064A2"/><w:left w:val="single" w:sz="8" w:space="0" w:color="8064A2"/><w:bottom w:val="single" w:sz="18" w:space="0" w:color="8064A2"/><w:right w:val="single" w:sz="8" w:space="0" w:color="8064A2"/><w:insideH w:val="nil"/><w:insideV w:val="single" w:sz="8" w:space="0" w:color="8064A2"/></w:tcBorders></w:tcPr></w:tblStylePr><w:tblStylePr w:type="lastRow"><w:pPr><w:spacing w:before="0" w:after="0" w:line="240" w:lineRule="auto"/></w:pPr><w:rPr><w:rFonts w:ascii="DengXian" w:eastAsia="Times New Roman" w:hAnsi="DengXian" w:cs="Times New Roman"/><w:b/><w:bCs/></w:rPr><w:tblPr/><w:tcPr><w:tcBorders><w:top w:val="double" w:sz="6" w:space="0" w:color="8064A2"/><w:left w:val="single" w:sz="8" w:space="0" w:color="8064A2"/><w:bottom w:val="single" w:sz="8" w:space="0" w:color="8064A2"/><w:right w:val="single" w:sz="8" w:space="0" w:color="8064A2"/><w:insideH w:val="nil"/><w:insideV w:val="single" w:sz="8" w:space="0" w:color="8064A2"/></w:tcBorders></w:tcPr></w:tblStylePr><w:tblStylePr w:type="firstCol"><w:rPr><w:rFonts w:ascii="DengXian" w:eastAsia="Times New Roman" w:hAnsi="DengXian" w:cs="Times New Roman"/><w:b/><w:bCs/></w:rPr></w:tblStylePr><w:tblStylePr w:type="lastCol"><w:rPr><w:rFonts w:ascii="DengXian" w:eastAsia="Times New Roman" w:hAnsi="DengXian" w:cs="Times New Roman"/><w:b/><w:bCs/></w:rPr><w:tblPr/><w:tcPr><w:tcBorders><w:top w:val="single" w:sz="8" w:space="0" w:color="8064A2"/><w:left w:val="single" w:sz="8" w:space="0" w:color="8064A2"/><w:bottom w:val="single" w:sz="8" w:space="0" w:color="8064A2"/><w:right w:val="single" w:sz="8" w:space="0" w:color="8064A2"/></w:tcBorders></w:tcPr></w:tblStylePr><w:tblStylePr w:type="band1Vert"><w:tblPr/><w:tcPr><w:tcBorders><w:top w:val="single" w:sz="8" w:space="0" w:color="8064A2"/><w:left w:val="single" w:sz="8" w:space="0" w:color="8064A2"/><w:bottom w:val="single" w:sz="8" w:space="0" w:color="8064A2"/><w:right w:val="single" w:sz="8" w:space="0" w:color="8064A2"/></w:tcBorders><w:shd w:val="clear" w:color="auto" w:fill="DFD8E8"/></w:tcPr></w:tblStylePr><w:tblStylePr w:type="band1Horz"><w:tblPr/><w:tcPr><w:tcBorders><w:top w:val="single" w:sz="8" w:space="0" w:color="8064A2"/><w:left w:val="single" w:sz="8" w:space="0" w:color="8064A2"/><w:bottom w:val="single" w:sz="8" w:space="0" w:color="8064A2"/><w:right w:val="single" w:sz="8" w:space="0" w:color="8064A2"/><w:insideV w:val="single" w:sz="8" w:space="0" w:color="8064A2"/></w:tcBorders><w:shd w:val="clear" w:color="auto" w:fill="DFD8E8"/></w:tcPr></w:tblStylePr><w:tblStylePr w:type="band2Horz"><w:tblPr/><w:tcPr><w:tcBorders><w:top w:val="single" w:sz="8" w:space="0" w:color="8064A2"/><w:left w:val="single" w:sz="8" w:space="0" w:color="8064A2"/><w:bottom w:val="single" w:sz="8" w:space="0" w:color="8064A2"/><w:right w:val="single" w:sz="8" w:space="0" w:color="8064A2"/><w:insideV w:val="single" w:sz="8" w:space="0" w:color="8064A2"/></w:tcBorders></w:tcPr></w:tblStylePr></w:style><w:style w:type="table" w:customStyle="1" w:styleId="Grigliachiara-Colore42"><w:name w:val="Griglia chiara - Colore 42"/><w:basedOn w:val="TableNormal"/><w:next w:val="LightGrid-Accent4"/><w:uiPriority w:val="62"/><w:rsid w:val="0013494A"/><w:rPr><w:rFonts w:ascii="Times New Roman" w:hAnsi="Times New Roman" w:cs="Times New Roman"/><w:lang w:val="fr-FR" w:eastAsia="fr-FR"/></w:rPr><w:tblPr><w:tblStyleRowBandSize w:val="1"/><w:tblStyleColBandSize w:val="1"/><w:tblBorders><w:top w:val="single" w:sz="8" w:space="0" w:color="8064A2"/><w:left w:val="single" w:sz="8" w:space="0" w:color="8064A2"/><w:bottom w:val="single" w:sz="8" w:space="0" w:color="8064A2"/><w:right w:val="single" w:sz="8" w:space="0" w:color="8064A2"/><w:insideH w:val="single" w:sz="8" w:space="0" w:color="8064A2"/><w:insideV w:val="single" w:sz="8" w:space="0" w:color="8064A2"/></w:tblBorders></w:tblPr><w:tblStylePr w:type="firstRow"><w:pPr><w:spacing w:before="0" w:after="0" w:line="240" w:lineRule="auto"/></w:pPr><w:rPr><w:rFonts w:ascii="DengXian" w:eastAsia="Times New Roman" w:hAnsi="DengXian" w:cs="Times New Roman"/><w:b/><w:bCs/></w:rPr><w:tblPr/><w:tcPr><w:tcBorders><w:top w:val="single" w:sz="8" w:space="0" w:color="8064A2"/><w:left w:val="single" w:sz="8" w:space="0" w:color="8064A2"/><w:bottom w:val="single" w:sz="18" w:space="0" w:color="8064A2"/><w:right w:val="single" w:sz="8" w:space="0" w:color="8064A2"/><w:insideH w:val="nil"/><w:insideV w:val="single" w:sz="8" w:space="0" w:color="8064A2"/></w:tcBorders></w:tcPr></w:tblStylePr><w:tblStylePr w:type="lastRow"><w:pPr><w:spacing w:before="0" w:after="0" w:line="240" w:lineRule="auto"/></w:pPr><w:rPr><w:rFonts w:ascii="DengXian" w:eastAsia="Times New Roman" w:hAnsi="DengXian" w:cs="Times New Roman"/><w:b/><w:bCs/></w:rPr><w:tblPr/><w:tcPr><w:tcBorders><w:top w:val="double" w:sz="6" w:space="0" w:color="8064A2"/><w:left w:val="single" w:sz="8" w:space="0" w:color="8064A2"/><w:bottom w:val="single" w:sz="8" w:space="0" w:color="8064A2"/><w:right w:val="single" w:sz="8" w:space="0" w:color="8064A2"/><w:insideH w:val="nil"/><w:insideV w:val="single" w:sz="8" w:space="0" w:color="8064A2"/></w:tcBorders></w:tcPr></w:tblStylePr><w:tblStylePr w:type="firstCol"><w:rPr><w:rFonts w:ascii="DengXian" w:eastAsia="Times New Roman" w:hAnsi="DengXian" w:cs="Times New Roman"/><w:b/><w:bCs/></w:rPr></w:tblStylePr><w:tblStylePr w:type="lastCol"><w:rPr><w:rFonts w:ascii="DengXian" w:eastAsia="Times New Roman" w:hAnsi="DengXian" w:cs="Times New Roman"/><w:b/><w:bCs/></w:rPr><w:tblPr/><w:tcPr><w:tcBorders><w:top w:val="single" w:sz="8" w:space="0" w:color="8064A2"/><w:left w:val="single" w:sz="8" w:space="0" w:color="8064A2"/><w:bottom w:val="single" w:sz="8" w:space="0" w:color="8064A2"/><w:right w:val="single" w:sz="8" w:space="0" w:color="8064A2"/></w:tcBorders></w:tcPr></w:tblStylePr><w:tblStylePr w:type="band1Vert"><w:tblPr/><w:tcPr><w:tcBorders><w:top w:val="single" w:sz="8" w:space="0" w:color="8064A2"/><w:left w:val="single" w:sz="8" w:space="0" w:color="8064A2"/><w:bottom w:val="single" w:sz="8" w:space="0" w:color="8064A2"/><w:right w:val="single" w:sz="8" w:space="0" w:color="8064A2"/></w:tcBorders><w:shd w:val="clear" w:color="auto" w:fill="DFD8E8"/></w:tcPr></w:tblStylePr><w:tblStylePr w:type="band1Horz"><w:tblPr/><w:tcPr><w:tcBorders><w:top w:val="single" w:sz="8" w:space="0" w:color="8064A2"/><w:left w:val="single" w:sz="8" w:space="0" w:color="8064A2"/><w:bottom w:val="single" w:sz="8" w:space="0" w:color="8064A2"/><w:right w:val="single" w:sz="8" w:space="0" w:color="8064A2"/><w:insideV w:val="single" w:sz="8" w:space="0" w:color="8064A2"/></w:tcBorders><w:shd w:val="clear" w:color="auto" w:fill="DFD8E8"/></w:tcPr></w:tblStylePr><w:tblStylePr w:type="band2Horz"><w:tblPr/><w:tcPr><w:tcBorders><w:top w:val="single" w:sz="8" w:space="0" w:color="8064A2"/><w:left w:val="single" w:sz="8" w:space="0" w:color="8064A2"/><w:bottom w:val="single" w:sz="8" w:space="0" w:color="8064A2"/><w:right w:val="single" w:sz="8" w:space="0" w:color="8064A2"/><w:insideV w:val="single" w:sz="8" w:space="0" w:color="8064A2"/></w:tcBorders></w:tcPr></w:tblStylePr></w:style><w:style w:type="paragraph" w:customStyle="1" w:styleId="Tabellaacapo"><w:name w:val="Tabella a capo"/><w:basedOn w:val="Normal"/><w:rsid w:val="00E04654"/><w:pPr><w:spacing w:after="40"/><w:jc w:val="left"/></w:pPr><w:rPr><w:rFonts w:ascii="Arial" w:hAnsi="Arial" w:cs="Times New Roman"/></w:rPr></w:style><w:style w:type="paragraph" w:customStyle="1" w:styleId="MandatoryRequirementList"><w:name w:val="Mandatory Requirement List"/><w:basedOn w:val="BodyText"/><w:rsid w:val="00D60692"/><w:pPr><w:widowControl w:val="0"/><w:numPr><w:numId w:val="16"/></w:numPr><w:tabs><w:tab w:val="clear" w:pos="0"/><w:tab w:val="clear" w:pos="360"/><w:tab w:val="clear" w:pos="851"/><w:tab w:val="clear" w:pos="5670"/><w:tab w:val="clear" w:pos="6096"/><w:tab w:val="num" w:pos="1494"/></w:tabs><w:spacing w:before="60" w:after="0"/><w:ind w:left="1491" w:hanging="357"/><w:jc w:val="both"/></w:pPr><w:rPr><w:rFonts w:ascii="Arial" w:hAnsi="Arial" w:cs="Times New Roman"/><w:i w:val="0"/><w:iCs w:val="0"/><w:kern w:val="24"/><w:sz w:val="20"/><w:szCs w:val="20"/><w:lang w:val="en-GB" w:eastAsia="fr-FR"/></w:rPr></w:style><w:style w:type="paragraph" w:styleId="ListParagraph"><w:name w:val="List Paragraph"/><w:basedOn w:val="Normal"/><w:uiPriority w:val="34"/><w:qFormat/><w:rsid w:val="00054C7F"/><w:pPr><w:ind w:left="720"/><w:contextualSpacing/></w:pPr><w:rPr><w:rFonts w:ascii="Arial" w:hAnsi="Arial" w:cs="Times New Roman"/><w:lang w:val="en-GB" w:eastAsia="fr-FR"/></w:rPr></w:style><w:style w:type="character" w:customStyle="1" w:styleId="Heading2Char"><w:name w:val="Heading 2 Char"/><w:aliases w:val="subtitle2 Char,Titre 2 modified Char,H2 Char,h2 Char,2 Char,sub-sect Char,RFQ1 Char,section header Char,21 Char,sub-sect1 Char,22 Char,sub-sect2 Char,23 Char,sub-sect3 Char,24 Char,sub-sect4 Char,25 Char,sub-sect5 Char,(1.1 Char,1.2 Char"/><w:link w:val="Heading2"/><w:rsid w:val="00CD6105"/><w:rPr><w:b/><w:bCs/><w:sz w:val="24"/><w:szCs w:val="24"/></w:rPr></w:style><w:style w:type="paragraph" w:customStyle="1" w:styleId="Stile8FIG"><w:name w:val="Stile8 FIG"/><w:basedOn w:val="Normal"/><w:link w:val="Stile8FIGCarattere"/><w:qFormat/><w:rsid w:val="00DE0434"/><w:pPr><w:ind w:firstLine="720"/><w:jc w:val="center"/></w:pPr><w:rPr><w:rFonts w:cs="Times New Roman"/><w:b/><w:color w:val="000080"/><w:lang w:eastAsia="fr-FR"/></w:rPr></w:style><w:style w:type="character" w:customStyle="1" w:styleId="Stile8FIGCarattere"><w:name w:val="Stile8 FIG Carattere"/><w:link w:val="Stile8FIG"/><w:rsid w:val="00DE0434"/><w:rPr><w:rFonts w:cs="Times New Roman"/><w:b/><w:color w:val="000080"/><w:lang w:eastAsia="fr-FR"/></w:rPr></w:style><w:style w:type="paragraph" w:styleId="BodyTextIndent2"><w:name w:val="Body Text Indent 2"/><w:basedOn w:val="Normal"/><w:link w:val="BodyTextIndent2Char"/><w:uiPriority w:val="99"/><w:semiHidden/><w:unhideWhenUsed/><w:rsid w:val="00696BA6"/><w:pPr><w:spacing w:after="120" w:line="480" w:lineRule="auto"/><w:ind w:left="283"/></w:pPr></w:style><w:style w:type="character" w:customStyle="1" w:styleId="BodyTextIndent2Char"><w:name w:val="Body Text Indent 2 Char"/><w:basedOn w:val="DefaultParagraphFont"/><w:link w:val="BodyTextIndent2"/><w:uiPriority w:val="99"/><w:semiHidden/><w:rsid w:val="00696BA6"/></w:style><w:style w:type="paragraph" w:customStyle="1" w:styleId="DocHeading1"><w:name w:val="Doc Heading 1"/><w:basedOn w:val="Normal"/><w:next w:val="Normal"/><w:rsid w:val="00696BA6"/><w:pPr><w:keepNext/><w:numPr><w:numId w:val="23"/></w:numPr><w:pBdr><w:bottom w:val="single" w:sz="12" w:space="1" w:color="000080"/></w:pBdr><w:spacing w:before="120" w:after="240"/><w:ind w:right="-284"/></w:pPr><w:rPr><w:rFonts w:cs="Times New Roman"/><w:b/><w:color w:val="000080"/><w:sz w:val="28"/><w:lang w:val="en-US" w:eastAsia="fr-FR"/></w:rPr></w:style><w:style w:type="paragraph" w:customStyle="1" w:styleId="DocHeading2"><w:name w:val="Doc Heading 2"/><w:basedOn w:val="Normal"/><w:next w:val="Normal"/><w:rsid w:val="00696BA6"/><w:pPr><w:keepNext/><w:numPr><w:ilvl w:val="1"/><w:numId w:val="23"/></w:numPr><w:spacing w:before="120" w:after="180"/><w:ind w:right="284"/></w:pPr><w:rPr><w:rFonts w:cs="Times New Roman"/><w:b/><w:color w:val="000080"/><w:sz w:val="24"/><w:lang w:val="en-US" w:eastAsia="fr-FR"/></w:rPr></w:style><w:style w:type="paragraph" w:customStyle="1" w:styleId="DocHeading3"><w:name w:val="Doc Heading 3"/><w:basedOn w:val="Normal"/><w:next w:val="Normal"/><w:rsid w:val="00696BA6"/><w:pPr><w:keepNext/><w:numPr><w:ilvl w:val="2"/><w:numId w:val="23"/></w:numPr><w:spacing w:after="180"/><w:ind w:right="284"/></w:pPr><w:rPr><w:rFonts w:cs="Times New Roman"/><w:b/><w:color w:val="000080"/><w:sz w:val="24"/><w:lang w:val="en-US" w:eastAsia="fr-FR"/></w:rPr></w:style><w:style w:type="paragraph" w:customStyle="1" w:styleId="Stile4"><w:name w:val="Stile4"/><w:basedOn w:val="Heading4"/><w:link w:val="Stile4Carattere"/><w:qFormat/><w:rsid w:val="00696BA6"/><w:pPr><w:keepNext/><w:numPr><w:numId w:val="23"/></w:numPr><w:overflowPunct w:val="0"/><w:autoSpaceDE w:val="0"/><w:autoSpaceDN w:val="0"/><w:adjustRightInd w:val="0"/><w:jc w:val="left"/><w:textAlignment w:val="baseline"/></w:pPr><w:rPr><w:rFonts w:ascii="Arial" w:hAnsi="Arial" w:cs="Arial"/><w:b/><w:bCs/><w:color w:val="000080"/><w:szCs w:val="24"/><w:lang w:eastAsia="fr-FR"/></w:rPr></w:style><w:style w:type="paragraph" w:customStyle="1" w:styleId="Stile5"><w:name w:val="Stile5"/><w:basedOn w:val="Heading5"/><w:link w:val="Stile5Carattere"/><w:qFormat/><w:rsid w:val="00696BA6"/><w:pPr><w:keepNext/><w:numPr><w:numId w:val="23"/></w:numPr><w:overflowPunct w:val="0"/><w:autoSpaceDE w:val="0"/><w:autoSpaceDN w:val="0"/><w:adjustRightInd w:val="0"/><w:jc w:val="left"/><w:textAlignment w:val="baseline"/></w:pPr><w:rPr><w:rFonts w:ascii="Arial" w:hAnsi="Arial" w:cs="Arial"/><w:b/><w:iCs/><w:color w:val="000080"/><w:sz w:val="18"/><w:szCs w:val="24"/><w:lang w:eastAsia="fr-FR"/></w:rPr></w:style><w:style w:type="paragraph" w:customStyle="1" w:styleId="Stile6"><w:name w:val="Stile6"/><w:basedOn w:val="Heading6"/><w:qFormat/><w:rsid w:val="00696BA6"/><w:pPr><w:keepNext/><w:numPr><w:numId w:val="23"/></w:numPr><w:overflowPunct w:val="0"/><w:autoSpaceDE w:val="0"/><w:autoSpaceDN w:val="0"/><w:adjustRightInd w:val="0"/><w:jc w:val="left"/><w:textAlignment w:val="baseline"/></w:pPr><w:rPr><w:rFonts w:ascii="Arial" w:hAnsi="Arial" w:cs="Arial"/><w:bCs/><w:color w:val="000080"/><w:sz w:val="18"/><w:szCs w:val="18"/><w:lang w:eastAsia="fr-FR"/></w:rPr></w:style><w:style w:type="character" w:customStyle="1" w:styleId="Stile5Carattere"><w:name w:val="Stile5 Carattere"/><w:link w:val="Stile5"/><w:rsid w:val="00696BA6"/><w:rPr><w:rFonts w:ascii="Arial" w:hAnsi="Arial" w:cs="Arial"/><w:b/><w:iCs/><w:color w:val="000080"/><w:sz w:val="18"/><w:szCs w:val="24"/><w:lang w:eastAsia="fr-FR"/></w:rPr></w:style><w:style w:type="character" w:customStyle="1" w:styleId="Stile4Carattere"><w:name w:val="Stile4 Carattere"/><w:link w:val="Stile4"/><w:rsid w:val="00696BA6"/><w:rPr><w:rFonts w:ascii="Arial" w:hAnsi="Arial" w:cs="Arial"/><w:b/><w:bCs/><w:color w:val="000080"/><w:szCs w:val="24"/><w:lang w:eastAsia="fr-FR"/></w:rPr></w:style><w:style w:type="paragraph" w:customStyle="1" w:styleId="DocNormal"><w:name w:val="Doc Normal"/><w:basedOn w:val="Normal"/><w:rsid w:val="0008300F"/><w:pPr><w:jc w:val="left"/></w:pPr><w:rPr><w:rFonts w:cs="Times New Roman"/><w:color w:val="000080"/><w:sz w:val="24"/><w:szCs w:val="24"/><w:lang w:val="en-GB" w:eastAsia="en-US"/></w:rPr></w:style><w:style w:type="paragraph" w:customStyle="1" w:styleId="DocAppendix"><w:name w:val="Doc Appendix"/><w:basedOn w:val="Normal"/><w:next w:val="Normal"/><w:rsid w:val="00E91448"/><w:pPr><w:keepNext/><w:pageBreakBefore/><w:numPr><w:numId w:val="25"/></w:numPr><w:pBdr><w:bottom w:val="single" w:sz="12" w:space="1" w:color="000080"/></w:pBdr><w:spacing w:before="120" w:after="240"/></w:pPr><w:rPr><w:rFonts w:cs="Times New Roman"/><w:b/><w:color w:val="000080"/><w:sz w:val="28"/><w:lang w:val="en-US" w:eastAsia="fr-FR"/></w:rPr></w:style><w:style w:type="paragraph" w:customStyle="1" w:styleId="DocAppendixHeading2"><w:name w:val="Doc Appendix Heading 2"/><w:basedOn w:val="Normal"/><w:next w:val="Normal"/><w:rsid w:val="00E91448"/><w:pPr><w:keepNext/><w:numPr><w:ilvl w:val="1"/><w:numId w:val="25"/></w:numPr><w:spacing w:before="120" w:after="180"/><w:ind w:right="284"/></w:pPr><w:rPr><w:rFonts w:cs="Times New Roman"/><w:b/><w:color w:val="000080"/><w:sz w:val="26"/><w:lang w:val="en-US" w:eastAsia="fr-FR"/></w:rPr></w:style><w:style w:type="paragraph" w:customStyle="1" w:styleId="DocAppendixHeading3"><w:name w:val="Doc Appendix Heading 3"/><w:basedOn w:val="Normal"/><w:next w:val="Normal"/><w:rsid w:val="00E91448"/><w:pPr><w:keepNext/><w:numPr><w:ilvl w:val="2"/><w:numId w:val="25"/></w:numPr><w:spacing w:after="180"/><w:ind w:right="284"/></w:pPr><w:rPr><w:rFonts w:cs="Times New Roman"/><w:b/><w:color w:val="000080"/><w:sz w:val="24"/><w:lang w:val="en-US" w:eastAsia="fr-FR"/></w:rPr></w:style><w:style w:type="table" w:styleId="LightShading-Accent1"><w:name w:val="Light Shading Accent 1"/><w:basedOn w:val="TableNormal"/><w:uiPriority w:val="60"/><w:rsid w:val="00112AF8"/><w:rPr><w:color w:val="365F91"/></w:rPr><w:tblPr><w:tblStyleRowBandSize w:val="1"/><w:tblStyleColBandSize w:val="1"/><w:tblBorders><w:top w:val="single" w:sz="8" w:space="0" w:color="4F81BD"/><w:bottom w:val="single" w:sz="8" w:space="0" w:color="4F81BD"/></w:tblBorders></w:tblPr><w:tblStylePr w:type="firstRow"><w:pPr><w:spacing w:before="0" w:after="0" w:line="240" w:lineRule="auto"/></w:pPr><w:rPr><w:b/><w:bCs/></w:rPr><w:tblPr/><w:tcPr><w:tcBorders><w:top w:val="single" w:sz="8" w:space="0" w:color="4F81BD"/><w:left w:val="nil"/><w:bottom w:val="single" w:sz="8" w:space="0" w:color="4F81BD"/><w:right w:val="nil"/><w:insideH w:val="nil"/><w:insideV w:val="nil"/></w:tcBorders></w:tcPr></w:tblStylePr><w:tblStylePr w:type="lastRow"><w:pPr><w:spacing w:before="0" w:after="0" w:line="240" w:lineRule="auto"/></w:pPr><w:rPr><w:b/><w:bCs/></w:rPr><w:tblPr/><w:tcPr><w:tcBorders><w:top w:val="single" w:sz="8" w:space="0" w:color="4F81BD"/><w:left w:val="nil"/><w:bottom w:val="single" w:sz="8" w:space="0" w:color="4F81BD"/><w:right w:val="nil"/><w:insideH w:val="nil"/><w:insideV w:val="nil"/></w:tcBorders></w:tcPr></w:tblStylePr><w:tblStylePr w:type="firstCol"><w:rPr><w:b/><w:bCs/></w:rPr></w:tblStylePr><w:tblStylePr w:type="lastCol"><w:rPr><w:b/><w:bCs/></w:rPr></w:tblStylePr><w:tblStylePr w:type="band1Vert"><w:tblPr/><w:tcPr><w:tcBorders><w:left w:val="nil"/><w:right w:val="nil"/><w:insideH w:val="nil"/><w:insideV w:val="nil"/></w:tcBorders><w:shd w:val="clear" w:color="auto" w:fill="D3DFEE"/></w:tcPr></w:tblStylePr><w:tblStylePr w:type="band1Horz"><w:tblPr/><w:tcPr><w:tcBorders><w:left w:val="nil"/><w:right w:val="nil"/><w:insideH w:val="nil"/><w:insideV w:val="nil"/></w:tcBorders><w:shd w:val="clear" w:color="auto" w:fill="D3DFEE"/></w:tcPr></w:tblStylePr></w:style><w:style w:type="table" w:styleId="LightShading"><w:name w:val="Light Shading"/><w:basedOn w:val="TableNormal"/><w:uiPriority w:val="60"/><w:rsid w:val="00112AF8"/><w:rPr><w:color w:val="000000"/></w:rPr><w:tblPr><w:tblStyleRowBandSize w:val="1"/><w:tblStyleColBandSize w:val="1"/><w:tblBorders><w:top w:val="single" w:sz="8" w:space="0" w:color="000000"/><w:bottom w:val="single" w:sz="8" w:space="0" w:color="000000"/></w:tblBorders></w:tblPr><w:tblStylePr w:type="firstRow"><w:pPr><w:spacing w:before="0" w:after="0" w:line="240" w:lineRule="auto"/></w:pPr><w:rPr><w:b/><w:bCs/></w:rPr><w:tblPr/><w:tcPr><w:tcBorders><w:top w:val="single" w:sz="8" w:space="0" w:color="000000"/><w:left w:val="nil"/><w:bottom w:val="single" w:sz="8" w:space="0" w:color="000000"/><w:right w:val="nil"/><w:insideH w:val="nil"/><w:insideV w:val="nil"/></w:tcBorders></w:tcPr></w:tblStylePr><w:tblStylePr w:type="lastRow"><w:pPr><w:spacing w:before="0" w:after="0" w:line="240" w:lineRule="auto"/></w:pPr><w:rPr><w:b/><w:bCs/></w:rPr><w:tblPr/><w:tcPr><w:tcBorders><w:top w:val="single" w:sz="8" w:space="0" w:color="000000"/><w:left w:val="nil"/><w:bottom w:val="single" w:sz="8" w:space="0" w:color="000000"/><w:right w:val="nil"/><w:insideH w:val="nil"/><w:insideV w:val="nil"/></w:tcBorders></w:tcPr></w:tblStylePr><w:tblStylePr w:type="firstCol"><w:rPr><w:b/><w:bCs/></w:rPr></w:tblStylePr><w:tblStylePr w:type="lastCol"><w:rPr><w:b/><w:bCs/></w:rPr></w:tblStylePr><w:tblStylePr w:type="band1Vert"><w:tblPr/><w:tcPr><w:tcBorders><w:left w:val="nil"/><w:right w:val="nil"/><w:insideH w:val="nil"/><w:insideV w:val="nil"/></w:tcBorders><w:shd w:val="clear" w:color="auto" w:fill="C0C0C0"/></w:tcPr></w:tblStylePr><w:tblStylePr w:type="band1Horz"><w:tblPr/><w:tcPr><w:tcBorders><w:left w:val="nil"/><w:right w:val="nil"/><w:insideH w:val="nil"/><w:insideV w:val="nil"/></w:tcBorders><w:shd w:val="clear" w:color="auto" w:fill="C0C0C0"/></w:tcPr></w:tblStylePr></w:style></w:styles>